Workbook

Sheet Raw Data
A1: Unique ID | B1: Archival Collection | C1: Archival Page (r/v) | D1: PDF Page | E1: Date* | F1: Source Location | G1: Source | H1: Source Title | I1: Target | J1: Target Title | K1: Relationship | L1: Cipher | M1: Topic | N1: Language | O1: Transcription | P1: Rough Translation | Q1: Notes
A2: ID_00001 | B2: ASF, Acquisti e Doni, Fol 142, Ins 8. | D2: 38 | E2: 1624/04/12 | F2: Pisa | G2: della Rena, Horatzio | H2: Beaurocrat: Seg.o dem.to | I2: von Habsburg, Maria Magdalena | J2: Ruler: Arciduchessa d'Austria e Gran Duchessa di Toscana | K2: Beaurocratic | O2: Maria Maddalea Arciduchessa d'Austria Gran Duchessa di Toscana Perche la Lavanda, che secondo l'Instituto nostro facciamo ogni Anno ai Poveri nela settimana Santa proceda con ordine, e maggior Devozione Voliamo che Il Canon__o m__ Paolo Tronci danoi espressa__e deputato, Quando ne detti giorni santi saremo In Pisa e legga ogni Anno per Il mercole di santo la mattina, tredici Donne, allequali laveremo li Piedi, et inoltre sette fanciullette, e sei fanciulli, e tutti siano confessati, e cominicati secondo l'eta' loro, et di haver cio eseguito ne habbino fede del Curato, e di questo il detto canonico ne avvisera' avanti, ed'ogn'altra cosa che bisogni portale effetto, Accio le cose passin con quiete e senza confus[io]ne. Havera' ancora particolar cura, che tali persone da eleggersi siano di buona fama povere vergognose, et originarie propie della citta' di Pisa, escludendo tutte l'altre, et avvertira', che la nostra Intension e', che d'una casa e famiglia della per manno cene sara' stato un suggetto, Il susseguente non vi deva piu essere Accio' dell'elemosina, che si da ne possin participare anco gli altri poveri, Per questo egli deve teneme in diligente Registro, e perche tali elezioni sino fatte con piu considerazione e giustizia, voliamo, et ordiniamo al mede s___ can__o che per questo fine, non deva ricever ne ammetter raccomandarne alcuna, Se ben fosse ben'ri stessi servition, e cortigiani. E quelle povere ancora che egli devra e legger p__nto rescritto particolae sieno con tutto cio visitate, e ritrovate habili, e con tutti i Requisiti, siammettin sub[it]o e quanto che no si escludino assolatamente che questa e' la nostra Volonta'. Dato In Pisa 12 Aprile 1624 | P2: Maria Maddalena, Archduchess of Austria, Grand Duchess of Tuscany So that the washing, which according to our Institute we perform each year for the Poor during Holy Week, may proceed with order and greater devotion, We wish Canon Paolo Tronci to give us express and delegated authority. When we are in Pisa on the said holy days and read every year on Holy Wednesday morning, thirteen women, whose feet we will wash, as well as seven girls and six boys, and all are to be confessed and sent according to their ages, and that they have performed this they are to have proof of this from the curate, and the said canon will advise us of this in advance, and anything else that needs to be done, so that matters may pass peacefully and without confusion. He will also take particular care that the people to be elected are of good reputation, poor, shameful, and native to the city of Pisa, excluding all others, and he will note that our intention is that if a subject of a house and family of the same household has been chosen, the next one must no longer be there. In order for the alms to be given, and for other poor people to be able to participate, he must keep a diligent register. And so that such elections are made with greater consideration and justice, we want and order the same person that for this purpose, he must not accept or admit any recommendation, even if they are from the same service and courtiers. And let those poor people, too, whom he will have to read and write in a particular way, be examined with all this, and found to be fit for purpose, and with all the requirements, be admitted immediately, and so long as they are not absolutely excluded, that this is our will. Dated in Pisa, April 12, 1624 | Q2: Una lettera in data di Pisa 12 Aprile 1624 - molte altre lettere e carte riguardarti il g____co del Ponte a Pisa con due ___ della medesime
A3: ID_00002 | B3: ASF, Acquisti e Doni, Fol 142, Ins 8. | D3: 40 | E3: 1623/02/19 | F3: Pisa | G3: della Rena, Horatzio | H3: Beaurocrat: Seg.o dem.to | I3: von Habsburg, Maria Magdalena | J3: Ruler: Arciduchessa d'Austria e Gran Duchessa di Toscana | K3: Beaurocratic | O3: Havendo la Serenissima Arciduchessa Granduchessa veduto con quanto affetto il Cavaliere Giovanbatista santa Proveditore dell'Arsanale protega il gioco del Ponte, Come persona conisciuta da S.A. molto a proposito in comandare alle quadre, lo deputa percio generale di tutta la gente da combattere Pero' non manche di far subito chiamare i detti Capitani di squadre, accio che essi sappinoda noi la nostra volonta' perche ciascuno virenda quella obbedienza che si deve come capo di tutti dalla quale ne procedono i buoni ordini, et la speranza delle Vittorie. Per queso il med.o generale non manche di ordinare i tutti che si mettino allord__e concordemente a fine che ___ si pronto perdar saggio di se med[esimo], et far prova del lor valore del quale SA si promette. | Q3: I think there is either a real or a make-believe/festival battle that Maria Maddalena is coordinating in the spring of 1623..? that's the sense I get from the 2 letters I transcribed and from skimming the documents from there to here; Ok apparently Gioco del Ponte is an annual Pisan festival that still goes on today. See the italian wikipedia page for an overview: https://it.wikipedia.org/wiki/Gioco_del_Ponte
A4: ID_00003 | B4: ASF, Acquisti e Doni, Fol 242, Ins 3. | D4: 5 | E4: 1609/08/22 | F4: Firenze/Fiorenza | G4: von Habsburg, Maria Magdalena | H4: Ruler: Arciduchessa d'Austria e Gran Duchessa di Toscana | I4: d'Elci, Orso | J4: Ambassador: Conte e Ambassadore | K4: Beaurocratic | O4: Ill.re Ambasc.re N.ro dilett.mo Noi scriviamo con l'aggiunta ha alla Maesta' della Regina in raccomandazione d'una lite che ha' in Napoli il Duca di Gravina, come potrete vedere dall'includo memoriale, et per che in essa ha interesse il signr Don Virginio Orsini Duca di Bracciano, per esser quel di Gravina suo parente, vogliamo che presentiate voi stesso la lettera a' S. M.ta quando pero ella si trovi in Madrid; et che le dimostriate anche in vote che questo negotzio mi e' particolarm.te a' cuore, et che pero' la supplichiate efficaccissimamente a' far dare in Napoli quelli ordini, di che l'ho' supplicata, per la buona et favorevole spedizione di quella lite per giustizia; et che procuriate ancora di far dare le lettere a voi, accio' che possiate inviale al medesimo G.D. Virginio, rimettendoci a' quel piu, che' S. Ecc.za medesima vi fara' intendere sopra questo negozio. Habbiamo mandato anche a S. M.ta un memoriale simile, pero' non ci occorre soggiugnervi altro il S.re Iddio vi conservi et contenti. | P4: Dearest Ambassador, We write with the addition to the Queen's Majesty in recommendation of a lawsuit that the Duke of Gravina is having in Naples, as you will be able to see from the enclosed memorial, and since Don Virginio Orsini, Duke of Bracciano, is interested in it, since the Duke of Gravina is her relative, we want you to present the letter to Her Majesty yourself when she is in Madrid; and to also show her in person that this matter is particularly close to my heart, and therefore to beg her most effectively to have the orders given in Naples, for which I have begged, for the good and favorable resolution of that lawsuit for justice; and that you also try to have the letters given to you, so that you can send them to the same G.D. Virginio, referring to what His Excellency Himself will tell you about this matter. We have also sent a similar memorandum to His Majesty, but we need not add anything else. May God keep you safe and happy.
A5: ID_00004 | B5: ASF, Acquisti e Doni, Fol 242, Ins 3. | D5: 6 | E5: 1609/10/13 | F5: Firenze/Fiorenza | G5: von Habsburg, Maria Magdalena | H5: Ruler: Arciduchessa d'Austria e Gran Duchessa di Toscana | I5: d'Elci, Orso | J5: Ambassador: Conte e Ambassadore | K5: Beaurocratic | O5: Il G. Don Virg:Orsino desidera, che la ser_ma sig_ra Arciduchessa gli faccia grazia di due lettere, l'una alla Maesta' della Regina di Spagna, et l'altra al Conte Orso d'Elci Ambasc__re di S. Alt.a in quella Corte, accio__ venga ordinato al Vice Re di Napoli in grazia dell'Alt.a Sua, che sia spedita con presta, et favorevole giustizia la Causa del Duca di Gravina per la pretensione, che ha' di dover succedere nello stato di Bisignano per la morte di Donna Giulia Orsina sua zia, il cui possesso gli viene ritardato per imputazione suscitategli contra de Don Iberio(?) Caraffa marito di d__a Sig__ra nello sparger voce, che ella sia morta di veleno per opera del Duca, beche apparischino del tutto vane dall'esser ella morta d'hidropisia benis__ conosciuta da' medici; oltre al dover essere alieni simili sospetti dalla persona del sud__ Duca, che e' tanto congiunto di sangue col G. Don Virginio, che egli ricevera' questo honore dalla benignita di S. Alt.a per fatto a' se medesimo(?) | P5: The Most Reverend Don Virg: Orsino wishes that the Most Serene Lady Archduchess grant him two letters, one to Her Majesty the Queen of Spain, and the other to Count Orso d'Elci, Ambassador of Her Highness to that Court, so that the Viceroy of Naples may be ordered, in thanks to Her Highness, to dispatch with prompt and favourable justice the Case of the Duke of Gravina for the claim he has to succeed to the state of Bisignano due to the death of Donna Giulia Orsina, his aunt, the possession of which is being delayed by accusations raised against him by Don Iberio(?) Caraffa, the Lady's husband, by spreading rumours that she died of poison at the hands of the Duke, although these rumours appear completely vain since she died of dropsy, which was well known to the doctors; in addition to the fact that such suspicions must be alien to the person of the southern Duke, who is so closely related by blood to the G. Don Virginio, that he will receive this honor from the benevolence of His Highness as a deed to himself(?)
A6: ID_00005 | B6: ASF, Acquisti e Doni, Fol 242, Ins 3. | D6: 8 | E6: 1609/08/22 | F6: Firenze/Fiorenza | G6: von Habsburg, Maria Magdalena | H6: Ruler: Arciduchessa d'Austria e Gran Duchessa di Toscana | I6: d'Elci, Orso | J6: Ambassador: Conte e Ambassadore | K6: Beaurocratic | O6: Ill__re sig__re Ambas__ N__ro dilett__mo. Oltre alla informazione che habbiamo delle vostre nobili et virtuose qualita', si fanno anche talm__te, sentire gl'effetti del buono et accetto servizio che tuttavia fate in cotesta carica, che Noi vi teniamo in quello honorato concetto che si deve al merito vostro, et vi testifichiamo d'haver molto particolarmente aggradito l'ossequente affetto di devozione, che ci havete mostrato con la v[ost]ra lettera, presentataci da mons__re Arcivescovo di Pisa nel suo ritorno. In tanto col servici costa' harete occasione di guadagnare ogni giorno piu' la benevolenza et grazia n[ost]ra; massima__te se ci darete spesso nuove della Maesta' della Regina et procurerete per via del P__re Riccardo suo Confessore, et di altri, et il s_re Iddio conservi | P6: Dearest Ambassador, In addition to the information we have of your noble and virtuous qualities, the effects of the good and acceptable service you are still performing in this office are also so felt that We hold you in that honorable opinion that is due to your merit, and We testify to you that We have particularly appreciated the obsequious affection and devotion that you have shown us with your letter, presented to us by the Archbishop of Pisa on his return. In the meantime, with your services you will have the opportunity to gain our benevolence and grace more and more every day; especially if you will give us frequent news of the Queen's Majesty and will try through Father Riccardo, her Confessor, and others, and may God preserve us. | Q6: he is explicitly tasked with getting information about the Queen THROUGH the confessor (and others). That's what happened during Cosimo's marriage negotiations but I thought it was super weird and shady... is this actually normal and chill, or is getting info from the confessor akin to trading in secrets or espionage? Maybe it isn't since this is MM getting updates on her own sister, who I assume she could just sort of write to whenever she wanted
A7: ID_00006 | B7: ASF, Acquisti e Doni, Fol 242, Ins 3. | D7: 11 | E7: 1610/09/02 | F7: Firenze/Fiorenza | G7: von Habsburg, Maria Magdalena | H7: Ruler: Arciduchessa d'Austria e Gran Duchessa di Toscana | I7: d'Elci, Orso | J7: Ambassador: Conte e Ambassadore | K7: Beaurocratic | O7: Ill__re Ambas__re ___ dilett__mo. Essendoci stato rappresentato da voi il contento che lor Maesta' Cattoliche hanno sentito del Nostro felice parto era ben dovesse che havesse anco luogo la vostra congratulatione particolare, la quale, sapendo Noi esser proceduta da vero devotissimo affetto habbiamo maggiormente aggradita. Vene facciamo fede con questa lora ma piu' velo ratificheremo con le opere ogni volta che havremo occasione d'impiegarci per vostro benefizio et honore, et dal s___re Iddio vi desideriamo prosperita'. | P7: Dearest Ambassador, Since you have expressed to us the joy that Their Catholic Majesties have felt about Our happy birth, it was fitting that your special congratulations should also take place, which, knowing that We have proceeded from truly devout affection, We have greatly appreciated. We bear witness to this with this hour, but we will ratify it more fully with our actions every time we have the opportunity to work for your benefit and honor, and from the Lord God we wish you prosperity. | Q7: Google Translate is translating "parto" to "birth," and I double checked with WordReference that "parto" does in fact mean "birth, childbirth, delivery."
A8: ID_00007 | B8: ASF, Acquisti e Doni, Fol 242, Ins 3. | D8: 13 | E8: 1610/10/09 | F8: Firenze/Fiorenza | G8: von Habsburg, Maria Magdalena | H8: Ruler: Arciduchessa d'Austria e Gran Duchessa di Toscana | I8: d'Elci, Orso | J8: Ambassador: Conte e Ambassadore | K8: Beaurocratic | O8: (to the Ambassador) Noi non havremmo il maggior gusto che di poter gratificare et servire la s__ra Contessa al'Altamira, la quale sappiamo molto bene che e' una s__ra di straordinario merito et di grandissimo valore, si che non ci moveremmo meno per il propio rispetto di lei, che per sapere quanto ella sia grata alla M__ta della Regina. Havendo Noi dunque sentito la richiesta che havete fatto per parte sua di raccomandare in Roma la spedizione del Diaconato di San Jac__o (Jacopo?) gia' proveduto nella persona d'un suo figlio, ne habbiamo scritto con ogni piu' efficace caldezza al s__re Cardinale dal Monte accio che informatosi dello stato di quel negotio, impieghi tutto il favore et l'autorita' sua difficulta' di tal natura che lo ritenghino indietro procuri di scoprirle, a' fine che dandosene avviso costa __ possa pensare a i rimedii di superarle. In somma, se harete occasione di vedere la d__ s__ra Contessa,, oltre al salutarla caram__te per parte nostra assicuratela pure che se bisognera' fare in Roma piu' d'una replica per tener sollecitato il negozio Noi lo faremo spontaneam__te et con la medesima affetione come su fusse cosa di Nostro proprio interesse come anco ci impiegheremo sempre volentierissimo in ogn'altra sua occorrenza. Dateci nuova con ogni Corriero della buona salute di lor Maesta' et de Principi et Principesse lor figliuoli; et il signore Iddio vi contenti. | P8: (to the Ambassador) We would have no greater pleasure than to be able to gratify and serve the Countess of Altamira, whom we know very well to be a lady of extraordinary merit and great value, so much so that we would be moved no less by our own respect for her than by knowing how grateful she is to Her Majesty the Queen. Therefore, having heard the request you made on her behalf to recommend to Rome the despatch of the Diaconate of San Jacopo (Jacopo?), already provided for in the person of one of her sons, we have written with the utmost fervor to Cardinal Dal Monte so that, having learned of the status of that matter, he may employ all his favor and authority to resolve any difficulties of a nature that may hold him back, so that, upon receiving notice, he may consider remedies to overcome them. In short, if you have the opportunity to see the Countess, in addition to greeting her kindly on our behalf, assure her that if it is necessary to make more than one visit to Rome to keep the business moving, we will do so spontaneously and with the same affection as if it were a matter of our own interest, just as we will always gladly contribute to any other need she may have. Please keep us informed by every courier of the good health of Their Majesties and of the Princes and Princesses, their children; and may the Lord God please you.
A9: ID_00008 | B9: ASF, Acquisti e Doni, Fol 242, Ins 3. | D9: 15 | E9: 1610/12/01 | F9: Firenze/Fiorenza | G9: von Habsburg, Maria Magdalena | H9: Ruler: Arciduchessa d'Austria e Gran Duchessa di Toscana | I9: d'Elci, Orso | J9: Ambassador: Conte e Ambassadore | K9: Beaurocratic | O9: (to the ambassador) Noi scriviamo alla M__ta della Regina in raccomandazione d'un desiderio del Marchese Gio:bata dal Monte (Cardinal del Monte or relative?) del tenore che vedrete dalla copia e vogliamo che presentiate voi stesso la lora accompagnandola in voce con quelle piu' efficaci parole che vi sovverranno, massimamente in testificatione del merito di questi sig__re molto ben conosciuti da voi, accio che con tanto maggior caldezza la M__ta sua habbia da favorire il negozio, il quale preme a' Noi grandem__te per le ragioni che habbiamo allegate nella detta letterea. E doppo che havrete fatto l'offitio con S. Mta siatene diligente promotore e sollecitatore appresso di tutti quelli che ci havranno da intervenire come se haveste da affaticarvi per Nostro particolare interesse, che tale stimiamo questo; e Dio vi conservi | P9: (To the ambassador) We write to the Queen's Majesty recommending a request from Marquis Giobata dal Monte (Cardinal del Monte or relative?) of the nature you will see in the copy. We ask you to present it yourself, accompanying it verbally with the most effective words you can think of, especially in testimony to the merit of these gentlemen, who are very well known to you, so that her Majesty may all the more fervently support the matter, which is of great importance to Us for the reasons we have set forth in the aforementioned letter. And after you have fulfilled your duties with Her Majesty, be a diligent promoter and solicitor of it to all those who will have to intervene, as if you were working for Our particular interest, for such We consider this to be the case; and God bless you.
A10: ID_00009 | B10: ASF, Acquisti e Doni, Fol 242, Ins 3. | D10: 17 | E10: 1610/02/10 | F10: Firenze/Fiorenza | G10: von Habsburg, Maria Magdalena | H10: Ruler: Arciduchessa d'Austria e Gran Duchessa di Toscana | I10: d'Elci, Orso | J10: Ambassador: Conte e Ambassadore | K10: Beaurocratic | O10: (to the ambassador) Noi scrivemmo gia' alla Maesta' della Regina, supplicandola a' favorire il sr felice di Gennaro, gentilhuomo Napolitano, per un luogo di Presidente, vacato per la morte del s__re scipione de curtis. Et per che il medesimo carico era anche chiesto da un altro Curtis, la qual famiglia e' stata sempre affezzionata di questa Casa, et il Gran Duca stesso scrisse alla Maesta' del Re in sua raccomandatione. Noi non ne facemmo instanza, se non in caso che il Curtis non ne fusse compiaciuto. Ora intendiamo che egli ne debbe essere escluso, et pero' se voi vi chiarirete che questo sia vero, vogliamo che opportunamente ricordiate, o' facciate ricordare alla Regina la Nostra richiesta in benefizio del Gennari, con assicurarla che questa gratia sara' ricevuta da Noi come propria; et il signore Iddio vi contenti.
A11: ID_00010 | B11: ASF, Acquisti e Doni, Fol 242, Ins 3. | D11: 20 | E11: 1611/06/08 | F11: Firenze/Fiorenza | G11: von Habsburg, Maria Magdalena | H11: Ruler: Arciduchessa d'Austria e Gran Duchessa di Toscana | I11: d'Elci, Orso | J11: Ambassador: Conte e Ambassadore | K11: Beaurocratic | M11: Recommendation | O11: E capitato qua' un giovane Tedesco, chiamato Gio: Ridolfo Vitzman suddito del serenissimo Arciduca Leopoldo nostro fratello nel vescovado d'Argentina, e ci ha' detto esser fuora della patria sua et anco privo de suoi beni per haver voluto lasciar heresie e ridursi a' vivere nella fede Cattolica; et essendosi risoluto di venire in Spagna per procurar qualche avviamento da poter vivere, ci haveva richiesto che Noi scrivessimo in sua raccomand__ne alla M.ta della Regina ma ci e' parso che basti di scrivere a' voi accio che sentiate le pretensioni di quest'huomo, e de qui vi giadichiate fino a qual segno convenga che ne parliate alla M.ta sua. Ci sara' ben caro che se vediete congiuntura buona da poterlo aiutare, o' in un modo o' in un altro voi lo facciate; e Dio vi conservi. | P11: A young German named Gio. Ridolfo Vitzman, a subject of the Most Serene Archduke Leopold, our brother in the bishopric of Argentina, arrived here. He told us that he was exiled from his homeland and deprived of his property because he had chosen to abandon heresies and return to living in the Catholic faith. Having resolved to come to Spain to find some means of support, he had asked us to write to recommend him to Her Majesty the Queen, but it seemed to us sufficient to write to you so that you might hear the man's claims and from there decide to what extent you should speak to Her Majesty about him. We would be very pleased if, if you see a good opportunity to help him, you would do so in one way or another; and God bless you. | Q11: Man claims to have been ousted from his home in Leopold V's Austria for being Catholic (because of the Protestant tensions there that led to the 30 years war etc), and has arrived in Florence but wants to go to Spain
A12: ID_00011 | B12: ASF, Acquisti e Doni, Fol 242, Ins 3. | D12: 22 | E12: 1611/07/22 | F12: Firenze/Fiorenza | G12: von Habsburg, Maria Magdalena | H12: Ruler: Arciduchessa d'Austria e Gran Duchessa di Toscana | I12: d'Elci, Orso | J12: Ambassador: Conte e Ambassadore | K12: Beaurocratic | O12: Ill. signore Cont'Orso Ambas.re nostro Dilett__mo Per. Il Leoni Corr__ Regio che passe a cote stavolta vi mand__mo in Rimvolto (?) ben ammagliato, dentro al quale a una vesta la quale per via de la s__ Contessa di Lemos, o, In quellla maniera, che piu parra' alla vostra prudenzia, Voliamo che presentiate in nostro nome alla M__ta della Regina di franc__a nostra nipote, et accompagniate questo Regalo, con quelle parole di complimento, che piu sonnerranno alla vostra discrezione, et che noi ci promettiamo dalla vostra destrezza, presentandola piu tosto come veste da viaggio, accio' tanto maggiorante venga scusato la tenuita' del Don__ et Honesto molto ardire. Dandoci poi __uviso che cosi l'haviate eseguisto, et Il s__ vi prosperi | P12: Illustrious Lord Count Orso, Our Most Beloved Ambassador, Per. Il Leoni, Royal Courier, who is passing by this time, we are sending you in a well-meshed wrapper (?), inside which is a dress which, by way of the Countess of Lemos, or, in whatever manner seems most to your prudence, We wish you to present in our name to the Lady of the Queen of France, our niece, and accompany this Gift with those words of compliment which will most please your discretion, and which we promise ourselves by your dexterity, presenting it rather as a travelling dress, so that the smallness of the Gift may be all the more excused and Honestly very bold. Then giving us approval that you have carried it out in this way, and may He prosper you.
A13: ID_00012 | B13: ASF, Acquisti e Doni, Fol 242, Ins 3. | D13: 24 | E13: 1611/09/12 | F13: Firenze/Fiorenza | G13: von Habsburg, Maria Magdalena | H13: Ruler: Arciduchessa d'Austria e Gran Duchessa di Toscana | I13: d'Elci, Orso | J13: Ambassador: Conte e Ambassadore | K13: Beaurocratic | M13: Childbirth | O13: Ill__ri Ambas__re Nostro dilett__mo. Essendoci ormai noto il devotiss__o affetto vostro verso di noi, stimavamo superflua la testifiazione della vostra allegrezza per l'ultimo felice parto che Dio ci ha concedato; non dimeno c'e' stata gratissima l'espressione fatta cene da voi per lettera; e vi confermiamo quella volonta' che altre volte havete potuto conoscere in Noi verso ogni vostro benefizio et onore, anzi con l'augmento che meritano le vostre virtu'. et il corso della buona e da noi molto agradita servitu' vostra in cotesta carica; e dal sig__re Iddio vi desideriamo ogni maggior bene | P13: Our beloved Illustrious Ambassadors, Since your most devoted affection for us is now known to us, we considered it superfluous to express your joy at the latest happy birth that God has granted us; nevertheless, the expression you expressed in your letter was most pleasing to us; and we confirm to you the desire that you have on other occasions been able to recognize in Us for all your benefits and honors, indeed for the increase that your virtues deserve, and the progress of your good and very welcome service in this office; and from the Lord God we wish you every greater good. | Q13: the ambassador congratulated MM on the birth of GiovanCarlo de' Medici (July 24 1611) and she says thanks
A14: ID_00013 | B14: ASF, Acquisti e Doni, Fol 242, Ins 3. | D14: 26 | E14: 1615/10/02 | F14: Cafaggiuolo | G14: von Habsburg, Maria Magdalena | H14: Ruler: Arciduchessa d'Austria e Gran Duchessa di Toscana | I14: d'Elci, Orso | J14: Ambassador: Conte e Ambassadore | K14: Beaurocratic | M14: Recommendation | O14: Dovera' esservi presentata questa dal signore Fran___ Mareri(?) Gentilhuomo Romano, il quale transferendosi costa' per alcuni suoi affari, riconera' all'opera, et aiuto vostro, per poter'essere tanto piu' facile, et favorevolmente spedito; et Noi, che desideriamo grandem__ di giovarli, per rispetto di chi cen'ha' ricerco, haveremo cariss__ oltre modo, che secondo le richieste, che di mano in mano egli vene fara' voi parliate a' favor suo in nome nostro, et a' s. m__ta, et al signore Duca di Lerma, et a' chiun___ altri bisogni; siche fatelo con ogni prontezza, et efficacia, et il signore Iddio vi conservi, et contenti | P14: This must be presented to you by Mr. Francesco Mareri(?), a Roman gentleman, who, having moved there for some business of his, will turn to your work and help, so that things can be much easier and more favorably expedited; and We, who greatly desire to help him, out of respect for those who have requested it, will be very kind, in particular, that according to the requests that he will make from time to time, you speak on his behalf in our name, and to his Majesty, and to the Lord Duke of Lerma, and to anyone else in need; so do it with all promptness and effectiveness, and may the Lord God preserve you and be happy. | Q14: basically a rec letter
A15: ID_00014 | B15: ASF, Acquisti e Doni, Fol 242, Ins 3. | D15: 28 | E15: 1615/10/22 | F15: Firenze/Fiorenza | G15: von Habsburg, Maria Magdalena | H15: Ruler: Arciduchessa d'Austria e Gran Duchessa di Toscana | I15: d'Elci, Orso | J15: Ambassador: Conte e Ambassadore | K15: Beaurocratic | M15: Intelligence | O15: Il Pre__ Pedro Garzes non e' ancora comparso qua', ma' Noi habbiamo in ogni modo ricevuto la lettera, che voi gli deste per Noi, et poi vedremo voltentieri ancor lui, quando egli passera' di qua'. Quelle Cifere lasciatevi in mano da lui, hacete fatto bene a' non mandarle, et le brucerete, et il signore Iddio vi conservi, et contenti | P15: you did well not to send the ciphers he gave you and (future tense, as if he hasn't done so yet and this is an instruction) burn them | Q15: a priest gave Orso d'Elci secret ciphers! MM says good job not forwarding them, burn them!
A16: ID_00015 | B16: ASF, Acquisti e Doni, Fol 242, Ins 3. | D16: 30 | E16: 1611/11/06 | F16: Siena | G16: von Habsburg, Maria Magdalena | H16: Ruler: Arciduchessa d'Austria e Gran Duchessa di Toscana | I16: d'Elci, Orso | J16: Ambassador: Conte e Ambassadore | K16: Beaurocratic | M16: Death | O16: Sappiamo che havreste voluto far con noi qualsivoglia altro offizio, che darci nuova cosi' dolorosa, come e' stata quella della morte della morte della M__ta' della Regina, Nostra amatissima sorella. ci e' stata non dimeno gratissima la condoglienza che n'havete fatta con esso noi, sapendo che e' proceduta dall'intimo del vostro cuore; poiche oltre al devotissimo affetto vostro verso il servizio di questa Casa ci e' nota la part_re osservanza che portavate a' quella benedetta anima, et la confidenza che ella haveva nella persona vostra. Questi rispetti accresceranno in Noi ogni di piu' l'inclinazione et la volonta' che portiamo al merito della vostra buona et accetta servita; et vela confermeremo anche con l'opere; e Dio vi contenti | P16: We know that you would have liked to do us any other service than to give us news as painful as that of the death of the Majesty of the Queen, Our most beloved sister. Nevertheless, the condolence you have expressed to us has been most grateful, knowing that it came from the depths of your heart; for, in addition to your most devoted affection for the service of this House, we are aware of the special respect you had for that blessed soul, and the confidence she had in you. These respects will further increase in Us the inclination and the will we have to merit your good and acceptable service; and we will also confirm it with our works; and may God please you. | Q16: Ambassador brought MM the news of her sister's death (Queen of Spain); Margaret is only 3 years older than MM and she died at age 26
A17: ID_00016 | B17: ASF, Acquisti e Doni, Fol 242, Ins 3. | D17: 35 | E17: 1612/06/19 | F17: Firenze/Fiorenza | G17: von Habsburg, Maria Magdalena | H17: Ruler: Arciduchessa d'Austria e Gran Duchessa di Toscana | I17: d'Elci, Orso | J17: Ambassador: Conte e Ambassadore | K17: Beaurocratic | M17: Death | O17: Ci e' dispiaciuta grandem__te la morte del P~re Riccardo Haller, gia' confessore della Regina Nostra sorella, perche lo conoscevamo per un buono e savio religioso, e percio' gli portavamo affezzione piu' che ordinaria. Habbiamo sentito la diligenza che havevate fatto accio' si mettessero da banda le scritture che egli teneva in lingua Alemanna, per farle abbruciare, ma se elle sono ancora in essere, desidereremmo che voi procuraste di farvele consegnare per mandarle qua' in Nostra mano, poiche una parte di esse sono uscite da Noi per farlo mostrare alla Maesta' della Regina, e quando bisogni dirne una parola al signore Duca di Lerma, fatelo per parte Nostra; e Dio vi conservi | P17: We were greatly saddened by the death of Father Richard Haller, former confessor of Our Sister Queen, because we knew him to be a good and wise religious man, and therefore we had a more than ordinary affection for him. We have heard of the diligence you have made to have the writings he kept in the German language put aside for burning, but if they are still in existence, we would like you to try to have them delivered to you so that we can send them here into Our hands, since some of them have been left by Us to be shown to the Queen's Majesty, and when it is necessary to say a word about them to the Lord Duke of Lerma, do so on Our behalf; and God save you. | Q17: Queen of Spain's confessor (is Riccardo Haller the same confessor she had while Ferdinando I was arranging Cosimo II's marriage who leaked information?); ok, really interesting about the Queen's confessor having writings from her in German that MM wants burned; I'm very interested in secrecy in these letters and I wonder if it warrants a chapter in the project... something called "Family Secrets" that analyzes the use of ciphers in family correspondence/important gov issues like marriage negotiations
A18: ID_00017 | B18: ASF, Acquisti e Doni, Fol 242, Ins 3. | D18: 37 | E18: 1612/07/10 | F18: Firenze/Fiorenza | G18: von Habsburg, Maria Magdalena | H18: Ruler: Arciduchessa d'Austria e Gran Duchessa di Toscana | I18: d'Elci, Orso | J18: Ambassador: Conte e Ambassadore | K18: Beaurocratic | M18: Recommendation | O18: La famiglia de Malvezzi di Bologna, come voi sapete, e' tanto conosciuta in Europa, che anco in cotesta corte crediamo esserne particolar notizia. E perche tutti hanno fatto sempre aperta professione d'esser serv__ri affezzionati e parziali di questa Casa, non habbiamo voluto mancare di compiacere il Signore Jacopo Malvezzi con una nostra raccomandazione, intoerno al suggetto contenuto nell'incluso suo memoriale. Non c'e' parso gia' conveniente di scrivere al Re medesimo, per non dargli moltestia con Nostre lettere in simili materie; ma commettiamo bene a' voi, che facciate offizio per il detto signore Jacopo, in tutto quello che conoscerete potergli giovare, parlandone non solamente a' i ministri principali ma anche a' S. M.ta medesima, se lo giudicherete opportuno, et che la qualita' della pretensioni vene diano animo; il che rimettiamo alla prudenza vostra, e Dio vi contenti | P18: The Malvezzi family of Bologna, as you know, is so well known in Europe that we believe it is well-known even in this court. And since they have always openly professed to be affectionate and sympathetic servants of this House, we did not want to fail to please Lord Jacopo Malvezzi with our recommendation regarding the subject contained in his enclosed memoir. We have not yet deemed it appropriate to write to the King himself, so as not to inconvenience him with our letters on similar matters; but we urge you to make an effort on behalf of the said Lord Jacopo in everything you know that can be of help to him, speaking about it not only to the principal ministers but also to His Majesty himself, if you deem it appropriate, and that the nature of the claims encourages you; which we leave to your prudence, and may God be pleased with you. | Q18: recommendation of Jacopo Malvezzi of Bologna
A19: ID_00018 | B19: ASF, Acquisti e Doni, Fol 242, Ins 3. | D19: 39 | E19: 1612/07/28 | F19: Firenze/Fiorenza | G19: von Habsburg, Maria Magdalena | H19: Ruler: Arciduchessa d'Austria e Gran Duchessa di Toscana | I19: d'Elci, Orso | J19: Ambassador: Conte e Ambassadore | K19: Beaurocratic | M19: Recommendation | O19: Volentieri sempre ci adoperemo per voi et per tutti i vostri parenti, et amici raccomandatici, come faremmo ancora al presente nella domanda del Dottor Jantoni, se non credessimo, che gia S.A. havessi determinato nell'animo suo il suggetto per questa Rutta; pero' non stimia__ poterne succedere altro. In altre occasioni saremo sempre pronte ad aiutarlo, et farli conoscere il conto, che facciamo della vostra intercessione, et restando con la solita buona volonta verso di voi preghiamo il Re vi prosperi | P19: We will always gladly do our best for you and for all your relatives and friends recommended to us, as we would do at present in response to Dr. Jantoni's request, if we did not believe that His Majesty had already determined in his mind the subject for this Rutta (role..?); however, we do not believe anything else could happen. On other occasions, we will always be ready to help him and let him know the value we have of your intercession, and remaining with the usual good will towards you, we pray that the King may prosper you. | Q19: Polite negative response to a recommendation
A20: ID_00019 | B20: ASF, Acquisti e Doni, Fol 242, Ins 3. | D20: 41 | E20: 1612/08/07 | F20: Firenze/Fiorenza | G20: von Habsburg, Maria Magdalena | H20: Ruler: Arciduchessa d'Austria e Gran Duchessa di Toscana | I20: d'Elci, Orso | J20: Ambassador: Conte e Ambassadore | K20: Beaurocratic | O20: Il contento che havete mostrato del nostro ultimo parto con salute e' stato conforme al vostro solito devotissimo affetto verso di Noi, e pero' habbiamo aggradito l'offizio quanto conveniva. Gia' sapevamo quanto era grata alla M.ta della Regina Nostra sorella che sia in Cielo, la servitu' della signora Duchessa di Gandia, e pero' ci e' stato accettissimo il complimento che ella ha' fatto con Noi, et nela ringraziamo con la risposta che sara' con questa; alla quale la presenterete, facendole anche fede in voce di quanto ella si puo' promettere di Noi nelle occorrenze di suo servizio. In proposito delle lettere et scritture che potesse havere il P~re Riccardo Haller (The Queen's confessor who recently passed away), non ci occorre replicar altro, havendo noi fatto tutta la diligenza che si poteva; e Dio vi conservi | P20: The happiness you have shown at our recent and healthy birth was consistent with your usual, most devoted affection toward Us, and therefore We have accepted the service as appropriate. We already knew how grateful the Queen, Our sister in Heaven, was for the service of the Duchess of Gandia, and therefore the compliment she paid Us was most welcome, and We thank her for it with the reply that will be included with this one, to which you will present her, also verbally confirming to her what she can promise of Us in the circumstances of her service. Regarding the letters and writings that Father Richard Haller (the Queen's confessor who recently passed away) may have, We need not reply further, having done all the diligence we could; and God bless you. | Q20: it's not clear what happened to the documents Father Richard Haller had from the Queen... it sounds like MM's two desired outcomes (either burn them or get them to her) may not have happened and she has dropped the issue, but I am not sure; also, another congrats on another birth. This time it must be about Margherita (31 May 1612). Was Margherita named for his sister Queen Margherita of Spain who just passed? That is such an interesting coincidence that her first daughter after the Queen's death is named Margarita, so I wonder if that is the case.
A21: ID_00020 | B21: ASF, Acquisti e Doni, Fol 242, Ins 3. | D21: 44 | E21: 1613/04/13 | F21: Firenze/Fiorenza | G21: von Habsburg, Maria Magdalena | H21: Ruler: Arciduchessa d'Austria e Gran Duchessa di Toscana | I21: d'Elci, Orso | J21: Ambassador: Conte e Ambassadore | K21: Beaurocratic | M21: Recommendation | O21: E' capitato qua ___ [vostro?] Cav__re di Malta Tedesco chiamato fra Gio:David Veiller, il quale raccontro di haver servito S Mta Catt[olic]a in mare con alcuni suoi Vasselli propii sotto la __ia del Conti Scerlei Inglese. Di poi dice esser venuto in discordia con il detto Conte per le cagioni che voi sentirete dall'aggiunto memoriale et egli stesso dovra' informarvi anche muoce, poiche due di voler venir a' cotesta Corte per questa, et altre sua pretensioni, et havendoci richesto(?) li qualche favore, non ci e' parso di poterne mancare, per essere egli di quella nazione, pero' ascoltatelo volentieri, et conoscendo che le sue doma[n]de habbino qualche appare__ra di giustitia, giovare, se bene ci rimettiamo alla prudenza vostra che facciate questo offitio fino a' quel segno che vi parra', et con le debiti coriospetione (?), et il signore Dio vi conservi | P21: A German Knight of Malta called Fra Gio:David Veiller happened to come here, and he said he served the Catholic Church at sea with some of his own vessels under the command of the English Count Scerlei. Then he says he has come into disagreement with the said Count for the reasons that you will hear from the attached memorial and he himself will also have to inform you of this, since two of them want to come to that Court for this and other pretensions of his, and having asked us (?) for some favor, it did not seem to us that we could refuse it, since he is of that nation, therefore listen to him willingly, and knowing that his requests have some appearance of justice, to help, although we leave it to your prudence to carry out this office up to the point that seems to you, and with the due consideration (?), and may the Lord God preserve you | Q21: There are a few occasions where someone asks MM for her aid and intercession and then MM tells Count Orso about it and basically passes the torch to him. So I guess this is her making good on her promises to intercede for those folks.
A22: ID_00021 | B22: ASF, Acquisti e Doni, Fol 242, Ins 3. | D22: 46 | E22: 1613/08/16 | F22: Firenze/Fiorenza | G22: von Habsburg, Maria Magdalena | H22: Ruler: Arciduchessa d'Austria e Gran Duchessa di Toscana | I22: d'Elci, Orso | J22: Ambassador: Conte e Ambassadore | K22: Beaurocratic | O22: Noi facevamo tanta stima della bonta' e del merito del Pre~ Riccardo Haller mentre egli visse che l'havevamo quasi in venerazione onde quando non havessimo altra notizia del Pre Pietro Garzes, ci basterebbe il sapere che egli sia stato compagno d'un si buon Religioso per tenerlo in un ottimo concetto come veram[ente?] lo teniamo. Alli giorni passati ricevemmo una sua lettera, per la quale ci fece un amorevolissimo saluto in nome di cotesti signore Principe e Principesse, offizio da noi sommamente gradito et apprezato. Pero' vogliamo che voi ringraziando per parte Nostra il detto Padre dell'ambasciata fattaci, lo preghiate ancora, che quando egli ne havra' opportuna occasione baci le mani per noi alli detti signori Principi et Principesse. __rendendo loro le nostre salutazioni affettuosissimamente Gli farete anche fede dell'affezzionata volonta' che portiamo a' lui, et che ci impiegheremo sempre volentierei per ogni suo benefizio e contento; e Dio vi conservi | P22: We had such high regard for the goodness and merit of Father Richard Haller while he lived that we almost held him in veneration. Even if we had no further news of Father Peter Garzes, it would be enough for us to know that he was the companion of such a good religious man to hold him in the highest regard, as we truly do. A few days ago we received a letter from him, in which he sent us a most loving greeting on behalf of the Prince and Princess, an office we have great gratitude and appreciation. Therefore, we wish you, while thanking the said Father on our behalf for the message he sent us, to also ask him to kiss the hands of the said Princes and Princesses for us when he has the appropriate opportunity. By returning our most affectionate greetings to them, you will also give proof of the affectionate desire we bear him, and that we will always willingly employ ourselves for his every benefit and happiness; and God keep you | Q22: Pietro Garzes is the SAME GUY who tried to give Count Orso ciphers and MM said to burn them. See PDF page 28.
A23: ID_00022 | B23: ASF, Acquisti e Doni, Fol 242, Ins 3. | D23: 48 | E23: 1613/10/03 | F23: Firenze/Fiorenza | G23: von Habsburg, Maria Magdalena | H23: Ruler: Arciduchessa d'Austria e Gran Duchessa di Toscana | I23: d'Elci, Orso | J23: Ambassador: Conte e Ambassadore | K23: Beaurocratic | O23: Il Duca di Gravina e' parente stretto del signore Don Virginio tanto congiunto con questa Casa quanto noi sapete, pero' mi par d'essere in obbligo di giovare alle cose sue in tutto quello che per me si possa Ci ha' fatto intendere di havere in cotesta corte alcune liti di non piccola importanza, et richiesstoci di favorirlo con nostre lettere. Vogliamo adunque che voi vi adoperiate in aiuto suo, parlandone non oblamente a' i preincipali ministri, et ad ogni altro che bisogni, ma a' S. Mta medesima, sene sareste richiesto dalli Agenti del detto Daca, iquali vi doveranno informare di tutto il negozio cosi(?) vene governereste in quel modo che vi dettera' la solita vostra prudenza, purche il Duca sappia che Noi vi habbiamo raccomandato questi suoi affari con molta caldezza; e Dio vi conservi | P23: The Duke of Gravina is a close relative of the lord Don Virginio, so closely connected with this House as we know, therefore I feel obliged to help him in all that I can. He has made it known to us that he has some disputes of no small importance at this court, and has asked us to assist him with our letters. We therefore want you to take action to help him, speaking about it not obliviously to the principal ministers, and to anyone else who is necessary, but to Her Majesty herself, if you are requested to do so by the agents of the said Duke, who must inform you of the entire affair, so that you will manage it in the way that your usual prudence dictates, provided that the Duke knows that We have recommended these affairs of his to you with great warmth; and God preserve you.
A24: ID_00023 | B24: ASF, Acquisti e Doni, Fol 242, Ins 3. | D24: 50 | E24: 1613/11/15 | F24: Firenze/Fiorenza | G24: von Habsburg, Maria Magdalena | H24: Ruler: Arciduchessa d'Austria e Gran Duchessa di Toscana | I24: d'Elci, Orso | J24: Ambassador: Conte e Ambassadore | K24: Beaurocratic | O24: Voi vedete dall'alligato foglio il merito de' servitti fatti a' coste sta Corona da Conte Marc'Antonio Malvezzi et la ragione ch'egli ha (di o chi?) pretendere la mercede, che chede a' S. Mta, o' d'un titolo di Marchese nel Regno di Napoli per suo aiuto di costa, o' d'una pensione; et perche oltre all'esser Cav. to molto degne, et stimabili qualita' et accett__ ser__ del Gran Duca costro signore et marito, e anche da noi molto amato, sentiremo volentieri, che abbracciando voi la sua Domanda gia' indotta, et assai bene incaminata da un suo Agente, per quanto egli ci affirma, facciati tutto quello, che sia possibile in aiuto del buon'effetto di essa scrivendone noi cosi efficacemente con approvatione, et licenza di S.A.; et Il [signore] Iddio vi conservi, et contento | P24: You see from the attached sheet the merit of the services rendered to this Crown by Count Marc'Antonio Malvezzi and the reason he has for asking for the mercede (compensation, reward?) he asks of His Majesty, either the title of Marquis in the Kingdom of Naples for his help in the cost, or a pension; and because, in addition to being a Knight of very worthy and estimable qualities and accepted servant of the Grand Duke, this lord and husband, and also much loved by us, we will gladly hear that, embracing his Request already induced, and very well directed by one of his Agents, as he affirms to us, you will do everything possible to help the good effect of it by writing to us so effectively with the approval and permission of His Highness; and may [Lord] God preserve you, and be pleased
A25: ID_00024 | B25: ASF, Acquisti e Doni, Fol 242, Ins 3. | D25: 53 | E25: 1614/02/06 | F25: Firenze/Fiorenza | G25: von Habsburg, Maria Magdalena | H25: Ruler: Arciduchessa d'Austria e Gran Duchessa di Toscana | I25: d'Elci, Orso | J25: Ambassador: Conte e Ambassadore | K25: Beaurocratic | O25: Scriviamo al Re Innsp__ [Innspruch?] della sua amorevolissime lettera, e voliamo che con S. Mta medesimo nel presentargliela, et con che vi pare a proposito significhiate Il dispiacer che haviamo havuto della Indisp[ensio]ne de serenissimi suoi figli nostre nipoti, della cui salute ci seriverete spesso premendoci molto, e furete anco sapere, che Madama Madre, et io procureremo, che sieno apparecchiati certi Remedii per levar' i segni del Vaiolo, che son sicure, e provati ne figli ______ Casa Et havremo anco caro, che ci ragguagliate qualche volta delle Cose di cotesta Corte, poiche non vi e' piu ness[un]o che se ne avvisi, et il [signore Iddio] vi prosperi | P25: We write to King Innsp__ [Innspruch?] of his most loving letter, and we want you to convey to His Majesty himself, in presenting it to him, and with what you think is appropriate, the regret we have had for the indispensability of his most serene children, our nipoti, about whose health you will often serve us by pressing us much, and you will also want to know that My Lady Mother (Christine of Lorraine, probably) and I will ensure that certain remedies are prepared to remove the signs of smallpox, which are safe and proven in the sons of the House. And we would also like you to inform us sometimes of the affairs of this Court, since there is no one left who takes notice of them, and may the Lord God prosper you.
A26: ID_00025 | B26: ASF, Acquisti e Doni, Fol 242, Ins 3. | D26: 55 | E26: 1616/04/15 | F26: Firenze/Fiorenza | G26: von Habsburg, Maria Magdalena | H26: Ruler: Arciduchessa d'Austria e Gran Duchessa di Toscana | I26: d'Elci, Orso | J26: Ambassador: Conte e Ambassadore | K26: Beaurocratic | M26: Recommendation | O26: Venendosene a cotesta Corte Ottavio Bernardi Gentilhomo Bolognese per suoi particolar negozii ci ha fatto ricercar di Volerci scrive__re In sua raccomandazione, et haviamo voluto compiacer' chi con ha richiesto, ma pero' con rimettere alla vostra discrezione, e solita prudenza Il farli in quelle occorrense che vi parrandi puro suo serv__o et nostra sodisfaccione. et Il signore vi prosperi | P26: Ottavio Bernardi, a gentleman from Bologna, having come to this Court for his particular business, has asked us to write to us on his recommendation, and we wanted to please those who have requested it, but we leave it to your discretion and usual prudence to do so in those cases where it seems to you to be his pure servant and to our satisfaction. And may the Lord prosper you. | Q26: She does "intercede" on behalf of everyone who asks, but really she just goes "hey this guy asked me for help and I said yes, but he's your problem now, do whatever you want." That's the sort of glib way of looking at it, obviously it is more complicated and speaks to the competence of Count Orso, their relationship, MM's obligations for interceding for basically anyone who asks, etc.
A27: ID_00026 | B27: ASF, Acquisti e Doni, Fol 242, Ins 3. | D27: 57 | E27: 1616/04/20 | F27: Firenze/Fiorenza | G27: von Habsburg, Maria Magdalena | H27: Ruler: Arciduchessa d'Austria e Gran Duchessa di Toscana | I27: d'Elci, Orso | J27: Ambassador: Conte e Ambassadore | K27: Beaurocratic | O27: La vostra lettera de 19 di febbraio cosi prina di ragguagli della buona salute di S. Mta et de i serenissimi sposi, et degli altri Infanti miei nipoti mi e stata grat__ma, et desidero, che andiate continuando di darmene spesso avviso, essendomi per l'osservanza, et affezion, ch'io gli porto, molto a' cuore il saperne nuove. Mi e stata anco oltre modo cara la notizia, che m'havete data di quello, vi ha' conferito il signore duca di Lerma, et della buona correspondenza, che cui ha promesso tener con esso voi per aumentarei la buona gratia di S. Mta, et come haviamo resoluto d'a__ttare le sue Amorevoli offerte, et il vostro consiglio, cosi volgiamo che nel presentargli le accluse gli rendiate gratie in nome nostro, soggiungendoli quelche piu parra' a proposito alla vostra destrezza, e prudenza, nella qual ci rimettiamo, e preghiamo Il signore che vi prosperi | P27: Your letter of February 19th, so full of information about the good health of His Majesty and of the Most Serene spouses, and of the other Infani, my nipoti, was grateful to me, and I desire that you continue to inform me of it often, since, due to the respect and affection that I bear him, I am very keen to hear news. I was also extremely pleased with the news you gave me of what the Lord Duke of Lerma has given you, and of the good correspondence he has promised to maintain with you to increase the good graces of His Majesty, and just as we have resolved to accept his loving offers and your advice, so we desire that in presenting him with the enclosed letters you return thanks in our name, adding whatever seems most appropriate to your dexterity and prudence, in which we rely, and we pray the Lord that you prosper. | Q27: the good health of His Majesty and of the most serene spouses..? This is 1616. Margaret died in 1611 and Phillip never remarried so I'm not sure what this means.
A28: ID_00027 | B28: ASF, Acquisti e Doni, Fol 242, Ins 3. | D28: 62 | E28: 1616/02/08 | F28: Firenze/Fiorenza | G28: von Habsburg, Maria Magdalena | H28: Ruler: Arciduchessa d'Austria e Gran Duchessa di Toscana | I28: d'Elci, Orso | J28: Ambassador: Conte e Ambassadore | K28: Beaurocratic | M28: Recommendation | O28: Sapete che altre volte haviamo scritto costa a favor'del Dottor Pompeo Battaglino, hora essendo vacata in Napoli nella sommaria una Piazza di Presid__te [or maybe Prend__te?] per morte del' Dottor Giulio Minadois, e venendo ricercata di volei di nouvo scriver al' signore Duca d'Uzeda accio' l'impetri haviamo voluto scriver' a voi solamente, e voliamo, che in quel miglior' modo, che giudicherete piu aproposito procuriate che il d__ Duca dacci offitio costa', e col Vice Re di Napoli per questa giusta pretensione del'Battaglino, e non mancate della solita vostra buona diligenza, che ne sentiremo molto piace, e nostro __ig__ vi prosperi | P28: You know that on other occasions we have written here in favor of Doctor Pompeo Battaglino, now that a Presid__te Square [or maybe Prend__te?] has been vacant in Naples due to the death of Doctor Giulio Minadois, and since we are asked to write again to the Lord Duke of Uzeda to obtain it, we wanted to write to you only, and we want you to ensure that the Duke gives us this office in the best way that you deem most appropriate, and with the Viceroy of Naples for this just claim of Battaglino, and do not fail in your usual good diligence, for we will be very pleased with it, and our good fortune to you.
A29: ID_00028 | B29: ASF, Acquisti e Doni, Fol 242, Ins 3. | D29: 64 | E29: 1618/03/15 | F29: Pisa | G29: von Habsburg, Maria Magdalena | H29: Ruler: Arciduchessa d'Austria e Gran Duchessa di Toscana | I29: d'Elci, Orso | J29: Ambassador: Conte e Ambassadore | K29: Beaurocratic | M29: Recommendation | O29: Viene al Capldhnle..? il Pre fra Gregorio da Rassina ministro de m__ oss__ti di Toscana, quale noi vi raccomandiamo, accio lo aiutiate in quelle honeste domande, e pretensioni di esser promosse al Diffinitorato [word crossed out i think], o' guardiano di herusalem/Gerusalem, che egli desidera rimettendocene pero' alla molta prudenza vostra, pregando il Sig__re che vi prosperi | P29: The priest Fra Gregorio da Rassina, minister of the monks of Tuscany, comes to ___, whom we recommend to you, so that you may help him in those honest requests and claims to be promoted to the office of [word crossed out i think], guardian of Jerusalem, which he desires, leaving it however to your great prudence, praying to the Lord that he may prosper you.
A30: ID_00029 | B30: ASF, Acquisti e Doni, Fol 242, Ins 3. | D30: 66 | E30: 1618/03/26 | F30: Firenze/Fiorenza | G30: von Habsburg, Maria Magdalena | H30: Ruler: Arciduchessa d'Austria e Gran Duchessa di Toscana | I30: d'Elci, Orso | J30: Ambassador: Conte e Ambassadore | K30: Beaurocratic | O30: Haviamo ricevuto la lettera del S. Mta che molto amorevolmente li scrive, et se bene era Inrisposta d__nra__ antecedente, haviam preso occasion del replicare e scriviamo ancora al Duca di Lerma, che potra' dar la lettera oportunamente e faverirci secondo Il suo solita, e voi potute in quel modo che pare a___ fargli haver l'accluso prego. Quanto alle tele d'oro per Il monast___o della Regina nostra sorella, che sia In cielo, vi si scrisse che Il tempo non poteva esser'bastante per con dur le a fine, ma non si manche __a sollecitarle piu che sia possibile nostro signore vi prosper__ | P30: We have received the letter from His Majesty, who writes to you very kindly, and although it was the previous reply, we have taken the opportunity to reply and we are writing again to the Duke of Lerma, who will be able to deliver the letter in a timely manner and assist us as usual, and you can do as you see fit by having the enclosed request. As for the gold cloth/canvas/fabric for the monastery of our sister Queen, who is in heaven, we wrote that there would not be enough time to complete them, but we will not fail to urge them as much as possible, our lord prospers you.
A31: ID_00030 | B31: ASF, Acquisti e Doni, Fol 242, Ins 3. | D31: 59-60 | E31: 1616/00/00 | F31: Firenze/Fiorenza | G31: von Habsburg, Maria Magdalena | H31: Ruler: Arciduchessa d'Austria e Gran Duchessa di Toscana | I31: d'Elci, Orso | J31: Ambassador: Conte e Ambassadore | K31: Beaurocratic | O31: Per continuar' la cominciata confidenza scriviamo al Re, et al Signore Duca di Lerma, et haviam[o] fatto capital del vostro prudente Avvertimento, mandando la lettera per S. Mta tutta di nostra m~a_ (?), et la Inviamo inclusa nel medesimo Piego del Esso signore Duca, che lo presenterete, accompagnandolo con quelle parole, che piu' vi parranno a preposito in rimostranza di detta confidenza, et del nostre Devotissimo affetto verso la Mta sua; Appresso desideriamo, che havendo Pietro Tacca (or Tava?) scultor del Cavallo, mandato a Donare al Re un Crucifisso di Bronzo, che a' venderlo qua' ne havria potuto cavar' due mila scudi, voi destram__e insinuasse al signore Duca di Lerma Il Primor dell'Artifizio d'esso, et il suo pregio, et poi concludesse, che havendo quest'Artefice di sup proprio moto donato si bell'opera ad un Re tanto potente, che egli ha sperato, che dalla sua Real mano, deva venir ricompensa piu', che equivalen__te et Informatelo ancor'che quest'huomo per la sua virtu' e' molto amato, et prezzato dal serenissimo Gran Duca, et da' me, Accio' che tanto piu volentier' S. Ecc__a habbia a protegerlo, et rappresentar' a' __ M.ta la conven__za del Remunerarlo. Rimettendo il resto alla Dilig[enza] et prudenza vostra; Volendo che haviate per raccomandato ancora Il Proposto di Massa duo frello [fratello], che e Venuto costa a' presentar Il Cavallo, ma avvertiretedi frattar In modo, che si il Re gli fara' alcuna mercede non apparisca fatta a conto nostro. Et Il signore riprosperi. | P31: To continue the confidence we have begun, we write to the King and to the Lord Duke of Lerma, and we have taken advantage of your prudent advice by sending the letter to His Majesty entirely from our mother (?), and we are sending it included in the same envelope from the Lord Duke, which you will present to him, accompanying it with those words which you consider most appropriate in demonstration of the said confidence and of our most devoted affection towards his Mother; We next desire that, since Pietro Tacca (or Tava?), the sculptor of the Horse, has sent a Bronze Crucifix to the King, which he could have sold here for two thousand crowns, you should dexterously insinuate to the Lord Duke of Lerma the origin of its workmanship and its value, and then conclude that since this Artist has of his own accord donated such a beautiful work to such a powerful King, he has hoped that from his Royal hand, a more than equivalent reward will come. and also inform him that this man, for his virtue, is much loved and prized by the Most Serene Grand Duke, and by me, so that His Excellency will be all the more willing to protect him and represent to the Majesty the King the appropriateness of remunerating him. Leaving the rest to your diligence and prudence. I want you to also have recommended the Provost of Massa, his brother, who came here to present the Knight, but you will take care to do so in such a way that if the King gives him any reward, it will not appear to have been done at our expense. And [basically God bless you] | Q31: just thinking here. it's a good thing to have BOTH maria maddalena and christine of lorraine at the medici court because even though those two nations are/have been at odds, they aren't completely at odds all the time. it is good to be allied with both of them when possible and only pick sides when you sort of have to. and anyway, Margaret and Phillip's daughter Anne is the Queen of France, so it's not like they aren't connected by blood just like every other important court
A32: ID_00031 | B32: ASF, Acquisti e Doni, Fol 243, Ins 5. | C32: 85r | D32: 102 | E32: 1623/07/08 | F32: Firenze/Fiorenza | G32: von Habsburg, Maria Magdalena | H32: Ruler: Arciduchessa d'Austria e Gran Duchessa di Toscana | I32: d'Elci, Orso | J32: Ambassador: Conte e Ambassadore | K32: Beaurocratic
A33: ID_00032 | B33: ASF, Acquisti e Doni, Fol 243, Ins 5. | C33: 87r | D33: 104 | E33: 1623/00/05 | F33: Firenze/Fiorenza | G33: von Habsburg, Maria Magdalena | H33: Ruler: Arciduchessa d'Austria e Gran Duchessa di Toscana | I33: d'Elci, Orso | J33: Ambassador: Conte e Ambassadore | K33: Beaurocratic
A34: ID_00033 | B34: ASF, Acquisti e Doni, Fol 243, Ins 5. | C34: 89r | D34: 106 | E34: 1623/06/06 | F34: Firenze/Fiorenza | G34: von Habsburg, Maria Magdalena | H34: Ruler: Arciduchessa d'Austria e Gran Duchessa di Toscana | I34: d'Elci, Orso | J34: Ambassador: Conte e Ambassadore | K34: Beaurocratic
A35: ID_00034 | B35: ASF, Acquisti e Doni, Fol 243, Ins 5. | C35: 91r | D35: 108 | E35: 1623/10/24 | F35: Firenze/Fiorenza | G35: von Habsburg, Maria Magdalena | H35: Ruler: Arciduchessa d'Austria e Gran Duchessa di Toscana | I35: d'Elci, Orso | J35: Ambassador: Conte e Ambassadore | K35: Beaurocratic
A36: ID_00035 | B36: ASF, Acquisti e Doni, Fol 243, Ins 5. | C36: 93r-93v | D36: 110-111 | E36: 1623/12/03 | F36: Firenze/Fiorenza | G36: von Habsburg, Maria Magdalena | H36: Ruler: Arciduchessa d'Austria e Gran Duchessa di Toscana | I36: d'Elci, Orso | J36: Ambassador: Conte e Ambassadore | K36: Beaurocratic
A37: ID_00036 | B37: ASF, Acquisti e Doni, Fol 243, Ins 5. | C37: 7r-7v | D37: 11-12 | E37: 0000/00/00 | F37: Firenze/Fiorenza | G37: von Habsburg, Maria Magdalena | H37: Ruler: Arciduchessa d'Austria e Gran Duchessa di Toscana | I37: d'Elci, Orso | J37: Ambassador: Conte e Ambassadore | K37: Beaurocratic | O37: Ill. Sig. Conte n[ost]ro diletti[ssi]mo Nel proponto del sig. Principe D. Lorenzo come ben dice VS in quanto ne scrive ultimam[en]te al Cardi[nale?] Cioli siamo gia tanto innanzi per ql che se n'e parlato et qui el [V or D?] Carlo Magal_tti et altri con M__d. suo frello [fratello] che non pare che su p___ far di meno di non mandarlo a renderli obbedienza per il Gran Duca et cosi egli come Noi ne stiamo de liberatam[en]te resoluti doppo essersi hoggi consultato q__ negotio su la lettera delle lre~ [del or Il?] s. Card[ina]le et di VS; Ma ben Vonemmo se possibil[e] fosse guadagnarei li l__rranta d[e]lla sala Regia poi che nel resto pe____ ___ la detto Mrs___ Magal_tti al _uada____ et egli refort_lo al ___ Card[ina]le n[ost]ro ci par d'esser sicuro d[e]l trattamento eguale a quello d[e]l Principe ___aso di Savora [Savoia?] et d[e]l Titolo di Alt.a et in questa pretensione ci siamo formati di ___rt_ anche doppo haver [sentito?] il de ____ di VS et nell'una et nell'altra parte che ne esso v__ebbe senta q.t assicura____ nel noi lo mandera___ altrimenti non dubitando [che or de?] o presto o ___di non habbiano p______ ______ di fare gli altri Principe quel ___ havera' fatto il Papa essendo il suo essempio il piu autentico et gia il __ Buca di Parma et altri Principi di Germania nassenamente danno delli Alt[ezz]_ al__ Principe D. Lorenzo et con gli Amb[assado]ri altri npn doveranno manchare de temperamento Pero' negghino pure il _ Card[ina]le et VS di an_____arse bene de que sa punto in que megliare et piu _____ niente
A38: ID_00037 | B38: ASF, Acquisti e Doni, Fol 243, Ins 5. | C38: 95r | D38: 113 | E38: 1623/08/00 | F38: Firenze/Fiorenza | G38: von Habsburg, Maria Magdalena | H38: Ruler: Arciduchessa d'Austria e Gran Duchessa di Toscana | I38: d'Elci, Orso | J38: Ambassador: Conte e Ambassadore | K38: Beaurocratic
A39: ID_00038 | B39: ASF, Acquisti e Doni, Fol 243, Ins 5. | C39: 97r | D39: 114 | E39: 1623/08/00 | F39: Firenze/Fiorenza | G39: von Habsburg, Maria Magdalena | H39: Ruler: Arciduchessa d'Austria e Gran Duchessa di Toscana | I39: d'Elci, Orso | J39: Ambassador: Conte e Ambassadore | K39: Beaurocratic
A40: ID_00039 | B40: ASF, Acquisti e Doni, Fol 243, Ins 5. | C40: 98r | D40: 115 | E40: 1623/12/20 | F40: Firenze/Fiorenza | G40: von Habsburg, Maria Magdalena | H40: Ruler: Arciduchessa d'Austria e Gran Duchessa di Toscana | I40: d'Elci, Orso | J40: Ambassador: Conte e Ambassadore | K40: Beaurocratic
A41: ID_00040 | B41: ASF, Acquisti e Doni, Fol 243, Ins 5. | C41: 101r-101v | D41: 117-118 | E41: 1623/00/13 | F41: Firenze/Fiorenza | G41: von Habsburg, Maria Magdalena | H41: Ruler: Arciduchessa d'Austria e Gran Duchessa di Toscana | I41: d'Elci, Orso | J41: Ambassador: Conte e Ambassadore | K41: Beaurocratic
A42: ID_00041 | B42: ASF, Acquisti e Doni, Fol 243, Ins 5. | C42: 103r | D42: 120 | E42: 1623/01/09 | F42: Villa Poggio Imperiale | G42: von Habsburg, Maria Magdalena | H42: Ruler: Arciduchessa d'Austria e Gran Duchessa di Toscana | I42: d'Elci, Orso | J42: Ambassador: Conte e Ambassadore | K42: Beaurocratic
A43: ID_00042 | B43: ASF, Acquisti e Doni, Fol 243, Ins 5. | C43: 105r-106r | D43: 122-124 | E43: 1623/07/13 | F43: Firenze/Fiorenza | G43: von Habsburg, Maria Magdalena | H43: Ruler: Arciduchessa d'Austria e Gran Duchessa di Toscana | I43: d'Elci, Orso | J43: Ambassador: Conte e Ambassadore | K43: Beaurocratic
A44: ID_00043 | B44: ASF, Acquisti e Doni, Fol 243, Ins 5. | C44: 107r | D44: 125 | E44: 1623/12/05 | F44: Firenze/Fiorenza | G44: di Lorena, Cristina | H44: Ruler: Gran Duchessa di Toscana | I44: d'Elci, Orso | J44: Ambassador: Conte e Ambassadore | K44: Beaurocratic
A45: ID_00044 | B45: ASF, Acquisti e Doni, Fol 243, Ins 5. | C45: 109r-110r | D45: 127-129 | E45: 1623/12/11 | F45: Firenze/Fiorenza | G45: di Lorena, Cristina | H45: Ruler: Gran Duchessa di Toscana | I45: d'Elci, Orso | J45: Ambassador: Conte e Ambassadore | K45: Beaurocratic
A46: ID_00045 | B46: ASF, Acquisti e Doni, Fol 243, Ins 5. | C46: 9r | D46: 13 | E46: 1623/01/03 | F46: Firenze/Fiorenza | G46: von Habsburg, Maria Magdalena | H46: Ruler: Arciduchessa d'Austria e Gran Duchessa di Toscana | I46: d'Elci, Orso | J46: Ambassador: Conte e Ambassadore | K46: Beaurocratic | O46: Il nostro Marchese Inghierami generale delle Galere non e' mai guarito del suo male anzi ha sempre dato all'indietro, et questa mattina haviamo havuto la mala nuova, che egli sia per caamminar poco innanzi, poiche li hanno gia dato l'olio santo. Nediamo conto a VS perche in caso che il sig. Cardinale mio Cognato (so this is Cardinal Carlo de' Medici) ne parlasse con esso lei, et __ esso entrassi in voler raccomandarci persona per conto del Marchesato, li possa rispondere, che il Granduca mio S.re et marito (this is Cosimo II, who is not alive at the time of this 1623 letter) essere questo Marchesato piu presto per honorar questo buono et bonemereto Cavaliere, che per altro conto, et sua vita durante et non altrimenti, si che venendo a' morte conforme alla volonta' di quell'Altezza verra' ad estinguersi, et ad annullarsi poiche se si havesse da permutare in altre persone, non comple al servizio del Granduca, ne de Vassalli; Pero' VS sapra' hora come si havra' da governare col s.r Card.le et il s.r __ola (Cioli?) conservi et contenti di fir.e li 3 di gennaio 1623 Il Prioratosi bene tra passa nel fratello et nipoti et linea masculina
A47: ID_00046 | B47: ASF, Acquisti e Doni, Fol 243, Ins 5. | C47: 111r | D47: 131 | E47: 1623/07/06 | F47: Firenze/Fiorenza | G47: von Habsburg, Maria Magdalena | H47: Ruler: Arciduchessa d'Austria e Gran Duchessa di Toscana | I47: d'Elci, Orso | J47: Ambassador: Conte e Ambassadore | K47: Beaurocratic
A48: ID_00047 | B48: ASF, Acquisti e Doni, Fol 243, Ins 5. | C48: 1r-1v | D48: 134-135 | E48: 1624/09/18 | F48: Firenze/Fiorenza | G48: von Habsburg, Maria Magdalena | H48: Ruler: Arciduchessa d'Austria e Gran Duchessa di Toscana | I48: d'Elci, Orso | J48: Ambassador: Conte e Ambassadore | K48: Beaurocratic | Q48: For some reason, the archival numbering starts over at this point. I guess because it is a new section of 1624 letters? But it is not labeled as a different folio or insert, so who knows.
A49: ID_00048 | B49: ASF, Acquisti e Doni, Fol 243, Ins 5. | C49: 3r-3v | D49: 136-137 | E49: 1624/05/09 | F49: Firenze/Fiorenza | G49: von Habsburg, Maria Magdalena | H49: Ruler: Arciduchessa d'Austria e Gran Duchessa di Toscana | I49: de' Medici, Carlo | J49: Clergy: Cardinale Decano e Principe di Toscana | K49: Close Family
A50: ID_00049 | B50: ASF, Acquisti e Doni, Fol 243, Ins 5. | C50: 4r | D50: 138 | E50: 1624/04/14 | F50: Pisa | G50: von Habsburg, Maria Magdalena | H50: Ruler: Arciduchessa d'Austria e Gran Duchessa di Toscana | I50: d'Elci, Orso | J50: Ambassador: Conte e Ambassadore | K50: Beaurocratic
A51: ID_00050 | B51: ASF, Acquisti e Doni, Fol 243, Ins 5. | C51: 6r-6v | D51: 140-141 | E51: 1624/01/01 | F51: Firenze/Fiorenza | G51: von Habsburg, Maria Magdalena | H51: Ruler: Arciduchessa d'Austria e Gran Duchessa di Toscana | I51: d'Elci, Orso | J51: Ambassador: Conte e Ambassadore | K51: Beaurocratic
A52: ID_00051 | B52: ASF, Acquisti e Doni, Fol 243, Ins 5. | C52: 8r | D52: 143 | E52: 1624/04/04 | F52: Pisa | G52: von Habsburg, Maria Magdalena | H52: Ruler: Arciduchessa d'Austria e Gran Duchessa di Toscana | I52: d'Elci, Orso | J52: Ambassador: Conte e Ambassadore | K52: Beaurocratic
A53: ID_00052 | B53: ASF, Acquisti e Doni, Fol 243, Ins 5. | C53: 9r-9v | D53: 144-145 | E53: 1624/05/22 | F53: Villa de Baroncelli | G53: von Habsburg, Maria Magdalena | H53: Ruler: Arciduchessa d'Austria e Gran Duchessa di Toscana | I53: d'Elci, Orso | J53: Ambassador: Conte e Ambassadore | K53: Beaurocratic
A54: ID_00053 | B54: ASF, Acquisti e Doni, Fol 243, Ins 5. | C54: 10r | D54: 146 | E54: 1624/03/02 | F54: Pisa | G54: von Habsburg, Maria Magdalena | H54: Ruler: Arciduchessa d'Austria e Gran Duchessa di Toscana | I54: d'Elci, Orso | J54: Ambassador: Conte e Ambassadore | K54: Beaurocratic
A55: ID_00054 | B55: ASF, Acquisti e Doni, Fol 243, Ins 5. | C55: 12r | D55: 148 | E55: 1624/03/27 | F55: Firenze/Fiorenza | G55: von Habsburg, Maria Magdalena | H55: Ruler: Arciduchessa d'Austria e Gran Duchessa di Toscana | I55: d'Elci, Orso | J55: Ambassador: Conte e Ambassadore | K55: Beaurocratic
A56: ID_00055 | B56: ASF, Acquisti e Doni, Fol 243, Ins 5. | C56: 11r | D56: 15 | E56: 1623/01/30 | F56: Firenze/Fiorenza | G56: von Habsburg, Maria Magdalena | H56: Ruler: Arciduchessa d'Austria e Gran Duchessa di Toscana | I56: d'Elci, Orso | J56: Ambassador: Conte e Ambassadore | K56: Beaurocratic | O56: Per questo che habbiamo poteto far noi, non mancammo di commettere che l'ordinario che era spedito a' Lione, fusse licenziato prestamente, poiche cosi haveva fatto instanza l'Ambasc.re doppo havergli dato il Dispaccio, lo trattenesse in Roma almeno quattro giorni, perche le lettere che il detto Ordinario ci porto', furono de 23 et egli arrivo' in firenze alli 29. Quanto alla Cecchina, poiche il Sig. Cardinale disidera che ella si fermi costa' per tutto questo Carnevale, noi contentiamo ch'ella lo serva. Et non havendo Noi che dir'altro in risposta dell'ultime lettere di VS ci bastera' ch'ella sappia che questa sera ce ne siamo tornati a' fiorenza, caccioati dal Poggio delle acque che sopraggiunsero, le quali havevano allagato tutti quei friani(?). Et Dio la conservi. Di fiorenza li 30 Genn. 1623 al Inc.ne
A57: ID_00056 | B57: ASF, Acquisti e Doni, Fol 243, Ins 5. | C57: 14r | D57: 150 | E57: 1624/05/08 | F57: Firenze/Fiorenza | G57: von Habsburg, Maria Magdalena | H57: Ruler: Arciduchessa d'Austria e Gran Duchessa di Toscana | I57: d'Elci, Orso | J57: Ambassador: Conte e Ambassadore | K57: Beaurocratic
A58: ID_00057 | B58: ASF, Acquisti e Doni, Fol 243, Ins 5. | C58: 16r-16v | D58: 152-153 | E58: 1624/05/06 | F58: Firenze/Fiorenza | G58: von Habsburg, Maria Magdalena | H58: Ruler: Arciduchessa d'Austria e Gran Duchessa di Toscana | I58: d'Elci, Orso | J58: Ambassador: Conte e Ambassadore | K58: Beaurocratic
A59: ID_00058 | B59: ASF, Acquisti e Doni, Fol 243, Ins 5. | C59: 18r | D59: 155 | E59: 1624/05/04 | F59: Ambrogiana | G59: von Habsburg, Maria Magdalena | H59: Ruler: Arciduchessa d'Austria e Gran Duchessa di Toscana | I59: d'Elci, Orso | J59: Ambassador: Conte e Ambassadore | K59: Beaurocratic
A60: ID_00059 | B60: ASF, Acquisti e Doni, Fol 243, Ins 5. | C60: 20r | D60: 157 | E60: 1624/05/20 | F60: Villa de Baroncelli | G60: von Habsburg, Maria Magdalena | H60: Ruler: Arciduchessa d'Austria e Gran Duchessa di Toscana | I60: d'Elci, Orso | J60: Ambassador: Conte e Ambassadore | K60: Beaurocratic
A61: ID_00060 | B61: ASF, Acquisti e Doni, Fol 243, Ins 5. | C61: 22r | D61: 159 | E61: 1624/04/03 | F61: Pisa | G61: von Habsburg, Maria Magdalena | H61: Ruler: Arciduchessa d'Austria e Gran Duchessa di Toscana | I61: d'Elci, Orso | J61: Ambassador: Conte e Ambassadore | K61: Beaurocratic
A62: ID_00061 | B62: ASF, Acquisti e Doni, Fol 243, Ins 5. | C62: 24r | D62: 161 | E62: 1624/03/27 | F62: Livorno | G62: von Habsburg, Maria Magdalena | H62: Ruler: Arciduchessa d'Austria e Gran Duchessa di Toscana | I62: d'Elci, Orso | J62: Ambassador: Conte e Ambassadore | K62: Beaurocratic
A63: ID_00062 | B63: ASF, Acquisti e Doni, Fol 243, Ins 5. | C63: 26r | D63: 163 | E63: 1624/03/11 | F63: Pisa | G63: von Habsburg, Maria Magdalena | H63: Ruler: Arciduchessa d'Austria e Gran Duchessa di Toscana | I63: d'Elci, Orso | J63: Ambassador: Conte e Ambassadore | K63: Beaurocratic
A64: ID_00063 | B64: ASF, Acquisti e Doni, Fol 243, Ins 5. | C64: 28r-28v | D64: 165-166 | E64: 1624/05/13 | F64: Villa de Baroncelli | G64: von Habsburg, Maria Magdalena | H64: Ruler: Arciduchessa d'Austria e Gran Duchessa di Toscana | I64: d'Elci, Orso | J64: Ambassador: Conte e Ambassadore | K64: Beaurocratic
A65: ID_00064 | B65: ASF, Acquisti e Doni, Fol 243, Ins 5. | C65: 30r-30v | D65: 169 | E65: 1624/04/19 | F65: Serravezza | G65: von Habsburg, Maria Magdalena | H65: Ruler: Arciduchessa d'Austria e Gran Duchessa di Toscana | I65: d'Elci, Orso | J65: Ambassador: Conte e Ambassadore | K65: Beaurocratic
A66: ID_00065 | B66: ASF, Acquisti e Doni, Fol 243, Ins 5. | C66: 32r | D66: 171 | E66: 1624/02/18 | F66: Pisa | G66: von Habsburg, Maria Magdalena | H66: Ruler: Arciduchessa d'Austria e Gran Duchessa di Toscana | I66: d'Elci, Orso | J66: Ambassador: Conte e Ambassadore | K66: Beaurocratic
A67: ID_00066 | B67: ASF, Acquisti e Doni, Fol 243, Ins 5. | C67: 13r-13v | D67: 17-18 | E67: 1623/08/21 | F67: Firenze/Fiorenza | G67: von Habsburg, Maria Magdalena | H67: Ruler: Arciduchessa d'Austria e Gran Duchessa di Toscana | I67: d'Elci, Orso | J67: Ambassador: Conte e Ambassadore | K67: Beaurocratic | O67: Vorremmo hormai(?) sentire, che il Papa fosse rimasto interamente netto di febbre [the Pope has a fever], et perfettamente risanato, et piaccia a Dio, de VS ci possa dar questa nuova con le p__, Il Conte Scipione d___a venire sempre che da lei sara' chiamato, cio' e' alla rinfrescata(?); Ma VS per il suo ritorno debbe haver disegnato di aspettare il Natale, perche tratta di arrivare in Maremma non potendo Noi credere, ch'ella pensi di potera an__ dare in tempi pero __l_si, come sono il Sett[emb]re, le Ott[ob]re; et bisogna l_ra considerare, se con buona conscienza ella possa star tanto lontana di qua'; S_gn_rno', de non vogliamo darle q.le centa troppo bisogno habbiamo della sua conservatione, et delle sua asci_tenza et il med[esimo] dicono Madama, et il Gran Duca. S_nt_ra VS gli de noi __ra diciamo nella lra di Madama in proposito della Amb.s da mandarsi, et ne staremo aspettando la sua risposta, et il suo parere. Quanto alla gente del ____ Card.le, an__mo considerando ql ch'ella scrive cio' e se d_ qua se ne debba mandar d_ll'altra; et intanto __ piace che ch_ ci, e', __a bene, et non so para male; et Il s. Iddio la conserv_ et prosperi. Da firenza 2__? Ag.o 1623
A68: ID_00067 | B68: ASF, Acquisti e Doni, Fol 243, Ins 5. | C68: 34r | D68: 173 | E68: 1624/03/04 | F68: Pisa | G68: von Habsburg, Maria Magdalena | H68: Ruler: Arciduchessa d'Austria e Gran Duchessa di Toscana | I68: d'Elci, Orso | J68: Ambassador: Conte e Ambassadore | K68: Beaurocratic | O68: Mi trovo questa settimana una lettera di VS la quale non contiene cosa che ricerchi risposta. Ma per non lasciar veniro questo Ordinario senza una mia, mi, bastoia dirle, che Madama la Gran Duchessa guari molto presto di quella In freddatura che le sopraggiunse, et il s.r Card.le et VS non se ne dovevano pigliar pensiero, perche quando il Picchena ne scrisse, (mostro/molto) pure che il male non era di consideratione, et lo fece, perche forse non fusse stato rappresentato da altri diversami __VS vedra' quolche il Gran Duca le scrive, et con la sua prudenza giudichera' che sia cosa di molta consideratione il vederle Armi forestiere(?), si puo dir le Porte delle nostre Citta', et io so che ella non manchera' di rappresentaio al Papa li inconvenienti che ne porsono nascere, perche dalla banda di qua saremo forlati di fare il medesimo. Hora che e' torna __ costa il Cav. Cioli, et che havra' tutte le scritture che bisognano, staremo aspettando d'intendere come s'incamineranno i negozii, et la piega che piglieranno, la quale voglio sperare che habbia da esser buona, medianto il consiglio et l'aiuta di VS. Et Dio la conservi. Di Pisa 4 Marzo 1624
A69: ID_00068 | B69: ASF, Acquisti e Doni, Fol 243, Ins 5. | C69: 36r | D69: 175 | E69: 1624/05/21 | F69: Villa de Baroncelli | G69: von Habsburg, Maria Magdalena | H69: Ruler: Arciduchessa d'Austria e Gran Duchessa di Toscana | I69: d'Elci, Orso | J69: Ambassador: Conte e Ambassadore | K69: Beaurocratic
A70: ID_00069 | B70: ASF, Acquisti e Doni, Fol 243, Ins 5. | C70: 38r | D70: 177 | E70: 1624/04/18 | F70: Sertana | G70: von Habsburg, Maria Magdalena | H70: Ruler: Arciduchessa d'Austria e Gran Duchessa di Toscana | I70: d'Elci, Orso | J70: Ambassador: Conte e Ambassadore | K70: Beaurocratic
A71: ID_00070 | B71: ASF, Acquisti e Doni, Fol 243, Ins 5. | C71: 40r | D71: 179 | E71: 1624/01/22 | F71: Villa Poggio Imperiale | G71: von Habsburg, Maria Magdalena | H71: Ruler: Arciduchessa d'Austria e Gran Duchessa di Toscana | I71: d'Elci, Orso | J71: Ambassador: Conte e Ambassadore | K71: Beaurocratic
A72: ID_00071 | B72: ASF, Acquisti e Doni, Fol 243, Ins 5. | C72: 42r | D72: 181 | E72: 1624/01/22 | F72: Villa Poggio Imperiale | G72: von Habsburg, Maria Magdalena | H72: Ruler: Arciduchessa d'Austria e Gran Duchessa di Toscana | I72: d'Elci, Orso | J72: Ambassador: Conte e Ambassadore | K72: Beaurocratic
A73: ID_00072 | B73: ASF, Acquisti e Doni, Fol 243, Ins 5. | C73: 44r | D73: 183 | E73: 1624/03/29 | F73: Livorno | G73: von Habsburg, Maria Magdalena | H73: Ruler: Arciduchessa d'Austria e Gran Duchessa di Toscana | I73: d'Elci, Orso | J73: Ambassador: Conte e Ambassadore | K73: Beaurocratic | O73: Non ci e' chi sappia meglio di VS la volonta' che Noi habbiamo havuto sempre di gratificare il Duca di Bracciano et la moglie, et i pagamenti che habbiamo lor fatti con nostro risico, s tante il sequestro di Napoli, Il quale non havendo essi fatto mai levare, e' segno che vi hanno trovato delle difficulta'. Et perche Madama la Gran Duchessa [Christine of Lorraine] et Io [Maria Maddalena] siamo Tutrici, e' obbligo nostro di avvertire, che per troppa facilita' nostra, il Gran Duca [Ferdinando] non riceva danno. Con tutto cio' premendo il s.r Cardinale che si dia al Duca questa sodisfazzione, si risponde a s. s. Ill.ma et l'Aud.re Antella ne devi scrivere anco a' VS che dandosi all Appalto cauzione idonea, di conservare indenne il Gran Duca, ogni volta che il denaro si trovasse esser mal pagato, noi procureremo che se ne faccia lo sborso per questa volta. Tanto potra' VS rispondere a' chi glie n'ha'parlato. Et il sig.re Iddio la prosperi. Di Livorno li 29 Marzo 1624 __
A74: ID_00073 | B74: ASF, Acquisti e Doni, Fol 243, Ins 5. | C74: 46r-46v | D74: 185-186 | E74: 1624/03/22 | F74: Livorno | G74: von Habsburg, Maria Magdalena | H74: Ruler: Arciduchessa d'Austria e Gran Duchessa di Toscana | I74: d'Elci, Orso | J74: Ambassador: Conte e Ambassadore | K74: Beaurocratic | O74: [to Count Orso] Faremo unitam[en]te risposta con questa sol lettera a' diverse gratissime vostre, e prima vi diremo, che quanto a quello, che ci avvisatesopra il neg[ozi]o dela Clausura dele Convertite di Siena, che quei ss.i Cardinali dela Congregazione desideravan di sapere, se altri Monasterii, e luogho pii fosser soliti tener nel Monte di Pieta' di Fiorenza i lor Danari per salvar ogni scrupolo, Vi diciamo assolutam[en]te, che molti, e molti monasteri, vene tengono, et con ogni sicurezza, Perche nell'ultima Riforma di d.Monte haviamo fatto veder, estudiar questo punto da gravissimi Theologi, e Dottori eminenti, e da Prelati Ecclesiastici, In somma hanno resoluto, et approvato tutti, che con sicura conscienzia vi si possin tenere -- Quanto poi alla Rendita, che noi intendiamo dar per il supplemento de gli alimenti di quelle Madri, di nostro Danaro, accio' sia sicura noi ne faremo un entrata perpetua fermata con buone scritta et ne daremo assegnamenti tali, che non vi sia punto punto da dubitare, e di tanto potiete assicurarne quegli Ill.mi della Congregazione -- Sentiamo grandem[en]te le male nuove, che ci date del sig.re Cardinale Gaetano, non sol per il dispiacer' di S.S.ta e per il danno, che ricevera' il sacro Colleg[io] d'un Valoroso suggetto, ma per la perdita, che fara' anco questa Casa d'un confidente cosi qualificato. Ma convien accomodarsi a' quel che piace al sig.re -- Per conto del maccabruni, che ha raccomandato per in Capitanato, com'anco del Caval. Placidi, Piccolhomini dela Triana, e Vecchi, noi haviamo ordinato, che ci sian ricordati al debito tempo, e se le informazioni corrisponderanno, non macheremo di far Capitale di quello, che avvisate, e di haverli Inconsiderazione Desiderando In queste, et altre occasioni dimostrarvi Il n[ost]ro solito affetoo, con il quale vi preghiamo dal sig.re ogni proper__ Di Livorno a 22 di marco 1624 an__
A75: ID_00074 | B75: ASF, Acquisti e Doni, Fol 243, Ins 5. | C75: 15r-15v | D75: 20 | E75: 1623/07/16 | F75: Firenze/Fiorenza | G75: von Habsburg, Maria Magdalena | H75: Ruler: Arciduchessa d'Austria e Gran Duchessa di Toscana | I75: de' Medici, Carlo | J75: Clergy: Cardinale Decano e Principe di Toscana | K75: Close Family | O75: ho recevuta la lettera di VS Ill.mo dell 14, et ho inteso con grandissimo mio contento il pensiero, che lei ha di questa casa, et quanto al esclusione del amico, ci pare a noi, che VS Ill.ma discorra' bene, ma perche noi non possiamo sapere, si occorrera, o, non, perche noi non possiamo sapere, si correra la lancia, o, no, VS Ill.ma potra discorrere di sopra col conte orso et col Car[dina]le di Monte, si parera a VS Ill.ma, et il conte, tal quale habiamo discorse qui, et loro, che son sul luogo, potrano sapere meglio quello, che ci comple per servivio di questa casa; basta far mi modo che non possino esser mai offesa di non per non potersi ricordare una volta, si li reuscisse il colpo; basta VS Ill.ma prudente, et si sapera' bene gubernare in qu__ta, et ogni altro cosa quanto al Car[dina]le ludovisia spediamo questa mattina apposta al Cont'Orso, che li faccia la offerta di tutto il nostro potera contro i Colonessi, et VS Ill.ma potra fare il medessimo quando sara a Roma, et con tutto l'affetto di cuore li baccio le mani. fiorenza 16 guglio 1623
A76: ID_00075 | B76: ASF, Acquisti e Doni, Fol 243, Ins 5. | C76: 17r | D76: 22 | E76: 1623/07/13 | F76: Firenze/Fiorenza | G76: von Habsburg, Maria Magdalena | H76: Ruler: Arciduchessa d'Austria e Gran Duchessa di Toscana | I76: d'Elci, Orso | J76: Ambassador: Conte e Ambassadore | K76: Beaurocratic | O76: Potrebbe avvenire, che __rricinandosi il s.r Cardinal nostro i Roma, ambedue gli Amb.ri di Francia et di Spagna volessero uscire ad incontrarlo, come volleso fare l'alrtra volta, et furono divertia per non sapersi da qual porta il s.r Card.le dovesse entrare. Hora venendo egli per la via di Perugia, nd si puo haver la ____ med[esi]ma et considerando Madama et io il disordine che ne nascerebbe, ci e' parso di darlo sapere i VS accio ella s'ingegni di ___arlo nel modo ___ parrsi alla sua prudenza, et in ogni caso spedisca un co.to incontro al s.r Card.le per avvisarlo di tutto, et Dio la conservi. Da fiorenza 14 Luglio 1623.Potrebbe avvenire, che __rricinandosi il s.r Cardinal nostro i Roma, ambedue gli Amb.ri di Francia et di Spagna volessero uscire ad incontrarlo, come volleso fare l'alrtra volta, et furono divertia per non sapersi da qual porta il s.r Card.le dovesse entrare. Hora venendo egli per la via di Perugia, nd si puo haver la ____ med[esi]ma et considerando Madama et io il disordine che ne nascerebbe, ci e' parso di darlo sapere i VS accio ella s'ingegni di ___arlo nel modo ___ parrsi alla sua prudenza, et in ogni caso spedisca un co.to incontro al s.r Card.le per avvisarlo di tutto, et Dio la conservi. Da fiorenza 14 Luglio 1623.
A77: ID_00076 | B77: ASF, Acquisti e Doni, Fol 243, Ins 5. | C77: 19r | D77: 24 | E77: 1623/11/07 | F77: Firenze/Fiorenza | G77: von Habsburg, Maria Magdalena | H77: Ruler: Arciduchessa d'Austria e Gran Duchessa di Toscana | I77: d'Elci, Orso | J77: Ambassador: Conte e Ambassadore | K77: Beaurocratic | O77: Nel negozio di Carlo Piccolomini per le considerazioni, che VS ci ha' accennato, si e' dato ordine, che il Contini sene venga quanto prima a' questa volta, et cosi Noi med.a potrimo piu' facilm[ente], et piu' chiaramente intendere, rimediare, et risolvere quelche convenga per quiete di tutte le parti. Et intorno all'altra breve lettera di VS de' 3 non habbiamo che replicare, rimettendoci a' quanto le scrive Madama, et il Picchena questa sera; et salutandola a' nome del Gran Duca, le desideriamo continue prosperita'. Di fio.za 7 9mre (I think september..?) 1623
A78: ID_00077 | B78: ASF, Acquisti e Doni, Fol 243, Ins 5. | C78: 21r | D78: 26 | E78: 1623/01/03 | F78: Firenze/Fiorenza | G78: von Habsburg, Maria Magdalena | H78: Ruler: Arciduchessa d'Austria e Gran Duchessa di Toscana | I78: d'Elci, Orso | J78: Ambassador: Conte e Ambassadore | K78: Beaurocratic | O78: Sul'attestazione, che ci fa' VS delle fatiche, et della buona servitu', che rende al s.r Cardinale nostro il suo M.ro di Stalla, ci siamo contentate di fargli la grazia, che ha desiderato, et la mandiamo pero con questa nelle mani di lei, accio' gliela consegni, o', gliela faccia havere; Nel resto le due lettere di VS di 26 et de 30 Xm.re (October?) non hanno bisogno di replica, poi cche quanto alle visite di __testi Amb.ri di Corone, et al Ricevimento da farsi costi al s.r Prpe [Principe] D. Lorenzo, ci rimetteremo a' quanto risolvere Voi altri ___, eta qualche le ne scrivera' il Picchena; et il sig.re Iddio la prosperi sempre. Noi volevamo questa mattina andare al Poggio a' quelle Caccie, __a' il tempo, che ancora non vuol fare pace, ci ha' impedito, ma' domani forse ce lo permettera'. Di fiorenza 3 Gennaio 1623___
A79: ID_00078 | B79: ASF, Acquisti e Doni, Fol 243, Ins 5. | C79: 23r | D79: 28 | E79: 1623/08/14 | F79: Firenze/Fiorenza | G79: von Habsburg, Maria Magdalena | H79: Ruler: Arciduchessa d'Austria e Gran Duchessa di Toscana | I79: d'Elci, Orso | J79: Ambassador: Conte e Ambassadore | K79: Beaurocratic | L79: Some | O79: Ho inteso volenteredalla ha di VS degli ____, ch'ella sia ______ sodisfatta de ql neg[ozi]o ____no a ch_ mi rimetto in tutto, e per tutto. Ci siamo rallegrate dela nuove n__gl__ della salute d[e]l Papa, et il s.r Iddio ce le conservi. Desideramo il suo ______, ma alla ri__f___scata, premendoci troppo la sua salute. Quanto alla cose di Urbano/Urbino VS vedra' ql, che le scrive di nostro ord. il Card[inale] Cioli: Non le scriveramo de nostra mano, per che essendola Vigilia della Madama sant.__ vogliamo attendere alle devozioni, et un q___ punto ce ne andiamo al Vespero, et di buon cure la salutiamo; et Il s.r Iddio la contenti: Di fiorenzia 14 Ag. 1623 In cambio d'un nepoteno, credo, che VA ne trovera' al suo ritorno in Casa d__ essendo gravida, et la Nuova(?) et la fog.__ D__ a ci d_g__a avviso di [encoded message]
A80: ID_00079 | B80: ASF, Acquisti e Doni, Fol 243, Ins 5. | C80: 25r-25v | D80: 30-31 | E80: 1623/07/23 | F80: Firenze/Fiorenza | G80: von Habsburg, Maria Magdalena | H80: Ruler: Arciduchessa d'Austria e Gran Duchessa di Toscana | I80: d'Elci, Orso | J80: Ambassador: Conte e Ambassadore | K80: Beaurocratic
A81: ID_00080 | B81: ASF, Acquisti e Doni, Fol 243, Ins 5. | C81: 27r-27v | D81: 33-34 | E81: 1623/00/27 | F81: Firenze/Fiorenza | G81: von Habsburg, Maria Magdalena | H81: Ruler: Arciduchessa d'Austria e Gran Duchessa di Toscana | I81: d'Elci, Orso | J81: Ambassador: Conte e Ambassadore | K81: Beaurocratic
A82: ID_00081 | B82: ASF, Acquisti e Doni, Fol 243, Ins 5. | C82: 29r-29v | D82: 36-37 | E82: 1623/08/08 | F82: Firenze/Fiorenza | G82: von Habsburg, Maria Magdalena | H82: Ruler: Arciduchessa d'Austria e Gran Duchessa di Toscana | I82: d'Elci, Orso | J82: Ambassador: Conte e Ambassadore | K82: Beaurocratic
A83: ID_00082 | B83: ASF, Acquisti e Doni, Fol 243, Ins 5. | C83: 31r-31v | D83: 39 | E83: 1623/12/28 | F83: Firenze/Fiorenza | G83: von Habsburg, Maria Magdalena | H83: Ruler: Arciduchessa d'Austria e Gran Duchessa di Toscana | I83: d'Elci, Orso | J83: Ambassador: Conte e Ambassadore | K83: Beaurocratic | O83: Dalla lettera di VS de 22 habbiamo sentito con molto gusto quanto ella haveva passato nell'Audienza con S. S.ta' et le amorevoli et cordiali parole che da lei le furono usate per confermar maggiormente quello che la S.ta S haveva gia' stabilito nel suo animo, di volere star sempre unita con questa Casa, et tener congiunti gli interessi suoi con quelli del Gran Duca. Et se bene Noi n'eravamo sicurissimi, havemdolo S. S.ta detto piu' volte, et cominciato a mostrarne anche gli effetti, non dimeno ci e' stata gratiss[im]a questa nuova asseverazione, et ne facciamo quel capitale, che richiedono parole di tanto peso, et d'un Papa che in ogni tempo e' stato tenuto per sincero et veridico. Pero' quando VS haura' occ[asio]ne di rivedere la S.ta S. vogliamo che ella glie ne renda efficacissime et affettuosiss[im]e grazie per parte di tutti Noi, et l'assicuri che dalla banda del Gran Duca le sara' corrisposto sempre con una ferma et stabile volonta', come S. B.ne et quelli del suo sangue lo conosceranno giornalmente dalle opere stesse. Et il Sig. Iddio la prosperi. Di fiorenza li 28 di Xbre (December) 1623
A84: ID_00083 | B84: ASF, Acquisti e Doni, Fol 243, Ins 5. | C84: 33r | D84: 41 | E84: 1623/01/10 | F84: Villa Poggio Imperiale | G84: von Habsburg, Maria Magdalena | H84: Ruler: Arciduchessa d'Austria e Gran Duchessa di Toscana | I84: d'Elci, Orso | J84: Ambassador: Conte e Ambassadore | K84: Beaurocratic | O84: Molto prudente, et molto accorto et stato il negoziato di VS con cotesti Amb.ri Regii, Ci resta hora, che Saglleri(??) stia sodo, che ci parra' gran Cosa, se ella non trova modo da legarlo stretto, ma' la destrezza di VS superera' ogni altra difficulta'. Del negozio di Urbino ci rimettiamo a' quanto scrive il Picchena, et l'Antella. et loro altri SS.ri si portano costi molto bene; et per che le due lettere sue de 6 non hanno bisogno d'altra replica, Prego Iddio, che illumini et il S.r Cardinale nostro, et VS per trovar modo di uscire di questi pensieri, et liberarne anche il d.r Duca di Urbino; et la saluto insieme col Gran Duca. Del Poggio X Gennaio (10th January) 1623 (Remember their new year was not in January but in March, so the year doesn't change just yet)
A85: ID_00084 | B85: ASF, Acquisti e Doni, Fol 243, Ins 5. | C85: 35r | D85: 43 | E85: 1623/12/12 | F85: Firenze/Fiorenza | G85: von Habsburg, Maria Magdalena | H85: Ruler: Arciduchessa d'Austria e Gran Duchessa di Toscana | I85: d'Elci, Orso | J85: Ambassador: Conte e Ambassadore | K85: Beaurocratic | O85: La lettera di VS degli 8 ci accenna quelche si possa sperare nel negozio di Urbino, del quale confidiamo particolarmente buono indirizzo con la prudenza di lei, A chi se bene questa mattina habbiamo inviata la lettiga per condurla qua'; Vogliamo non di meno, che vedendo ella, che vi sia ancora bisogno costi della persona sua per il sud.o negotio, si fermi pure finche le parra' a' proposito, Perche la lettiga tanto consuma costa', quanto qua' et noi ci importa il trattenerla poco, o', assai; Habbiamo bene sentito con gran contento nostro, quelche VS ha' trattato col s.r Cardinale Barberino, et con Mons[igno]re Magalotti per gli interessi, et bisogni di Alemagna, et hauremo caro, che ella ne rinuovi tutti quegli offizii, che conoscera' opportuni per tanto buon'opera; et il S.re Iddio inspiri a' lei, et acotesti S.S.ri quelche sia meglio per queste Turbulenze, et le conceda buon viaggio, et ogni altra prosperita'. Di fiorenza 12 Xbre 1623
A86: ID_00085 | B86: ASF, Acquisti e Doni, Fol 243, Ins 5. | C86: 37r | D86: 45 | E86: 1623/07/29 | F86: Firenze/Fiorenza | G86: von Habsburg, Maria Magdalena | H86: Ruler: Arciduchessa d'Austria e Gran Duchessa di Toscana | I86: d'Elci, Orso | J86: Ambassador: Conte e Ambassadore | K86: Beaurocratic | O86: Passa un Corr.ro di Francia, et habbiamo voluto rispondere alla lettera di VS di 22 essendoci stati gratissimi quei particolariscritti a' Madama Ser.ma, et anche habbiamo sentito volentieri, che il governo dela Casa del sig.re Cardinale nostro vada bene. Ma ci maravigliamo infinitam[en]te, che in questi gran caldi camminino con tanta freddezza le cose del Conclave, et bisognera' pero' riscaldare quei SS.ri Cardinali. Noi ci godiamo questa buona bagnatura d'Arno, et il Gran Duca ancora, Il quale saluta VS, et sta' aspettando qualche nuova di costa', et Il s.re Iddio la conservi, et prosperi. Di fiorenza 29 Lug.o 1623
A87: ID_00086 | B87: ASF, Acquisti e Doni, Fol 243, Ins 5. | C87: 39r-40r | D87: 47-49 | E87: 1623/01/23 | F87: Firenze/Fiorenza | G87: von Habsburg, Maria Magdalena | H87: Ruler: Arciduchessa d'Austria e Gran Duchessa di Toscana | I87: d'Elci, Orso | J87: Ambassador: Conte e Ambassadore | K87: Beaurocratic | O87: I termini che Mons. Santorio uso' col s.re Duca d'Urbino, dovettono esser tali, che quel buon Vecchio hebbe grandissima cagione di scandalezzarsi, et d'entrare in sospetto che contro di lui si volesse procedere con modi violenti, poiche venne fino a' chiedergli che mettesse nelle fortezze huomini confidenti del Papa, o' gli desse i contrassegni. Oltra di questo si sa' che intorno a' S. Leo sono stati fatti diversi aggiramenti che in Pesaro sono stati mandati de capitani sotto finito pretesto d'esser disgustati delle ecclesiastici che in un convento di S. Francesco vicino a una Porta di quella Citta' habbino andato alcuni frati da fazzione, et habili a' potersi impodronire della detta Porta. Et si sa' ancora che per tutte le Terre delle Chiese da quelle bande, non si sente et non si vede altro che arme, et che Mons. Verospi in Perugia non attende ad altro che a' riveder la fortezza et le munizioni, et ad assoldar capitani et soldati come se l'Italia fusse in un manifesto pericolo di guerra. Onde non e' maraviglia che il sig. Duca d'Urbino, potendo con molta ragione sospettare che tutti questi apparecchi si faccino contro di lui, habbia un forzato i suoi presidii, et fatto delle altre cose, per assicurarsi da qualche stravagante insulto che gli potesse venire addosso; vedendo che non habbia giovato punto tutto quello che egli s'e' ingegnato di fare, et con lettere, et con ogni altra sorte di dimostrazione, per sincerare il Papa, et per esser lasciato vivere in pace; et pure ha dato hormai tanti segni di pasienza, et d'animo quieto, che forse son parsi troppi. Merita a dunque il sig.re Duca che ogn'uno lo scusi appresso di S. S.ta se vedendo tanti preparamenti dalla parte degli ecclesiastici, ha fatto anch'egli rinforzare i presidiinelle sue Pianze, per non ricevere qualche affronto, et per voler'esser padrone, come e', mentre che vive. Con tutto cio' noi non mancheremo, secondo l'avvertimento di VS, di far tutti quelli offizii, che Madama et Io giodicheremo opportuni ma vorremmo ancora che dalla banda di corta si procurasse di rappresentare al Papa, che i suoi ministri son quelli che danno occasione lle novita', et a' i disgurti: Et che si come ogn'uno crede, che tutte queste dimostrazioni si faccino contro la mente et il volere di S. S.ta cosi ella provegga in maniera che il Duca non venga provocato, ne messo in necessicta' di far cose contrarie alla sua natura. Questo offizio vorremmo che VS facesse con la S.ta Sua, accio' ella non solamente scusasse il Duca, ma lo compatisse de travagli, che gli vengono dati sul fine della sua vita, et della sua Casa. Quanto a Duca di Pastrana, replichiamo che le cose d'Urbino camminano oggi in una maniera, che egli per termine del suo carico, dovrebbe entraarci da se stesso, non essendo cosa che prema piu' al suo Re', che la pace et quiete d'Italia.Et sentendo che per lo stato ecclico non risuona altro che arme, egli vorrebbe saperne la cagione, poiche si potrebbe correr pericolo, che tutti i Principi, d'Italia facessero il medesimo, Il che non potrebbe piacere a S. M.ta' Et che se questi apparecchi fussero per lei cose d'Urbino non vede che ci sia bisogno alcuno di circondar con l'arme un Principe, che e' serv.re del Re, et che non domanda altro che la sua quiete, et di esser lasciato vivere in pace. Insomma a' Madama et a' me parrebbe, che a' VS con la destrezza, potesse facilmente venir fatto, di far cadere il Duca di Pastrana in questo concetto da se stesso, et cosi pigliar'occasione di discorrer con esso lui, di quello che si potesse operar col Papa intorno a' questo negozio. ___________ havendo Pastrana potuto squadrar piu' volte la _____ condizione di S. S.ta sapra' giudicar molto bene l'________ possino partorire i suoi offizii, et conseguentem[en]te _______ _oluzione piu' ferma, credendosi sempre qui, che _____ ____te ottima del Papa non si possino fare se non ottime ____i. Et Dio la conservi. _____ del Poggio li 23 di Genn. 1623 ab. Inc.ne
A88: ID_00087 | B88: ASF, Acquisti e Doni, Fol 243, Ins 5. | C88: 1r | D88: 5 | E88: 1623/07/05 | F88: Illegible | G88: von Habsburg, Maria Magdalena | H88: Ruler: Arciduchessa d'Austria e Gran Duchessa di Toscana | I88: d'Elci, Orso | J88: Ambassador: Conte e Ambassadore | K88: Beaurocratic | O88: Nel ritorno di Battaglino haviamo intiso il gran caldo che V.S. ha havuto, il che ce ne e' dispiaciuto quanto ella puo immaginarsi, poiche haviamo particolar desiderio che ella si conservi cosi buona salute; Hora che ella e' a__icata costi havra' campo di riposarsi et di ristorarsi Mando a V.S. una lettera del Cardinale dal Monte, et veduta che l'havra ci potra' mandare a' dire quelche le doviamo risponde re. Attenda ad havessi cura, et el __ la guard di firenze li 5 di luglio 1623
A89: ID_00088 | B89: ASF, Acquisti e Doni, Fol 243, Ins 5. | C89: 41r-41v | D89: 51-52 | E89: 1623/00/00 | F89: Firenze/Fiorenza | G89: von Habsburg, Maria Magdalena | H89: Ruler: Arciduchessa d'Austria e Gran Duchessa di Toscana | I89: d'Elci, Orso | J89: Ambassador: Conte e Ambassadore | K89: Beaurocratic
A90: ID_00089 | B90: ASF, Acquisti e Doni, Fol 243, Ins 5. | C90: 43r | D90: 54 | E90: 1623/10/17 | F90: Firenze/Fiorenza | G90: von Habsburg, Maria Magdalena | H90: Ruler: Arciduchessa d'Austria e Gran Duchessa di Toscana | I90: d'Elci, Orso | J90: Ambassador: Conte e Ambassadore | K90: Beaurocratic | O90: Havendo Noi approvato il prudente parer di VS dl tenersi la Principessa sposa appresso la Mre per quella buona ragione considerata da lei; et d___endo la mre entrare in Monasterio, e', necessario, che otteniamo licenza da S. S.ta di potervi mettere anche lei con __e Donne, una della quali sara' Vedova, et l'altra _____amo sapere, se d___eremo eleggerla co', Vedova co', fanciulla; Pero' VS sara' contenta, con participation, et con Da__ del s.r Cardinale, di supplicar S. S.ta __ q. licenza, et procurarne la speditione piu' ___lle cetamente, che sia possibile, per mandarcela sub[ito?]; et altro non ci ___e con q. et Il __ Iddio la conservi, et contenti: Da firenza 17 Ottobre 1623 Dovendo l_______ mandar la licenza per la Mre ___ staff__, se alta occ[asio]ne non mi s__ V. la mandera q. alta con la med[esim]a
A91: ID_00090 | B91: ASF, Acquisti e Doni, Fol 243, Ins 5. | C91: 45r | D91: 56 | E91: 1623/02/18 | F91: Pisa | G91: von Habsburg, Maria Magdalena | H91: Ruler: Arciduchessa d'Austria e Gran Duchessa di Toscana | I91: d'Elci, Orso | J91: Ambassador: Conte e Ambassadore | K91: Beaurocratic | O91: Alle lettere di VS de X [10] et degli 11 ho poco da dire in risposta, perche quanto alla proporta fatta dal Sig.re Lodovico Ridolfi, di transferire in uno de nostri figliuoli i Benefizii che egli tiene in Uratis lavia, il Picchena d'ordine mio scrisse a VS dall'Ambrogiana quanto occorreva, mentr'Io ero quel giorno a' caccia. Et essendosi data commessione in Vienna all'Ambasc[ado]re Altoviti di procurare fedele informazione di quei Benefizii, aspetteremo il ragguaglio che da lui cene sara' dato, innanzi che si faccia altro. Intanto VS potra' far ringraziare il Sig. Lodovico del suo pensiero, con dire che ci andremo pensando, et al suo tempo gli si fara' intendere la nostra risoluzione, con quelle parole che a VS parranno convenienti. Per conto di Monreale ho'scritto all'Arciduca Leopoldi mio frello, del Memoriale che ha' presentato al Papa quell'Arcivescovo, et l'ho' pregato a' mandar quanto prima la Procura per poter transferire la pensione, et spedirne le Bolle; et per maggior facilita' gli ho' mandato quella formula di Procura che ci fu' gia' inviata di corta'. Noi venimmo hiersera a' Pisa con cattivissimo tempo, il quale anche oggi dura molto tempe_toso, siche' faremo un carnevale senza alcun trattenimento. Barta che tutti stiamo con salute per grazia d'Iddio, il quale conservi VS in buona prosperita'. Da Pisa 18 di febraio 1623 _____
A92: ID_00091 | B92: ASF, Acquisti e Doni, Fol 243, Ins 5. | C92: 47r-47v | D92: 58 | E92: 1623/01/22 | F92: Villa Poggio Imperiale | G92: di Lorena, Cristina | H92: Ruler: Gran Duchessa di Toscana | I92: d'Elci, Orso | J92: Ambassador: Conte e Ambassadore | K92: Beaurocratic | O92: Io che so molto bene quanto il Cavalier di sillerii sia discreto, et prudente, et che ha fatto professione fino ad hora d'essere affezzion~ a' questa Casa, non ho mai dubitato, che egli non fusse per mostrarsitale vero l'Ambas.re Albizi venuto a' rendere obbed.a a S. S.ta in nome del Gran Duca. Ho havuto dunque piacere di sentire dalle lettere de VS che ne sia seguito l'effetto con segni di molta amorevolezza, et vorrei, che egli saperse, che tutti noi ne restiamo con obligo alla sua cortesia, et io in particolare Pero' VS con buona opportunita' glie ne faccia larga testimon.a assicurandolo, che io ne conservero' grata memoria, et che non desidero altro se non che egli mi dia occasione di fargli conoscere dall'opere stesse quanto io habbia stimato questa sua amorevole di mostrazione, et Dio la conservi Dalla Villa del Poggio li 22 genn.o 1623
A93: ID_00092 | B93: ASF, Acquisti e Doni, Fol 243, Ins 5. | C93: 3r | D93: 6 | E93: 1623/12/15 | F93: Firenze/Fiorenza | G93: von Habsburg, Maria Magdalena | H93: Ruler: Arciduchessa d'Austria e Gran Duchessa di Toscana | I93: d'Elci, Orso | J93: Ambassador: Conte e Ambassadore | K93: Beaurocratic | O93: sig.re Conto io me son trovato in un gran in___ con la sua lettera perche me fu resa in preso_bia di Madama [CL] et ella volse subito sapere quel esto lei _n_ scrivesse si bene io disso che non tiratasse de altro che delle cosse della Mirandola(?) et di Valditato(?) in ogni modo lei ha __suto leg_re da se non me dava mia altra p__role si non dove lei dico per amor dol p. __Don lorenzo che io et lei mostriamo far ogni cosa __sunti__ per amor di Madama perso si lei mi vuolo scrivere della cose che lei man vuole che Madama vegga me mandi da ogni ma___ che lettere per il Conte Raimisi(?) sico figlio et io mi ricoman di nelle suo orationi in quelle santi luogi et tem_i
A94: ID_00093 | B94: ASF, Acquisti e Doni, Fol 243, Ins 5. | C94: 49r | D94: 60 | E94: 1623/01/17 | F94: Villa Poggio Imperiale | G94: von Habsburg, Maria Magdalena | H94: Ruler: Arciduchessa d'Austria e Gran Duchessa di Toscana | I94: d'Elci, Orso | J94: Ambassador: Conte e Ambassadore | K94: Beaurocratic | O94: Comparse qua' il Barechini due giorni sono al'habbiamo visto volentieri, et sentito con molto gusto le relazioni, che ci ha fatto delle cose di cotesta Corte, et della sanita' di VS, Dalla quale stiamo hora aspettando l'avviso delle visite, che saranno passate fra' cotesti Amb. (Regii..?), et il nro d'obedienza, et le spriamo senza intoppi, secondo che ella ci scrive; Siamo Tutti al Poggio, essendovi comparsa anche Madama Ser.ma da due giorni in qua', et se bene vi habbiamo gran freddi non sono pero' crudeli, come VS rappresenta essere costa'; Perche le giornate vanno molto belle, et con sole, et finche questo non e' scoporto, non andiamo la mattina in Caccia, et ritorniamo poi la sera con esso, Talche non sentiamo trato gran freddo, come pare, che senta costi VS; Procuri pero' di difendersene in tutti i modi, per conservarsi sana, che e' quanto desideriamo, et quanto ci sovviene di replicare alle 3. lettere sue de 4. 9. et 12. et il s.re Iddio la prosperi. Dalla Villa del Poggio 17 Genn. 1623
A95: ID_00094 | B95: ASF, Acquisti e Doni, Fol 243, Ins 5. | C95: 51r | D95: 62 | E95: 1623/10/09 | F95: Firenze/Fiorenza | G95: von Habsburg, Maria Magdalena | H95: Ruler: Arciduchessa d'Austria e Gran Duchessa di Toscana | I95: d'Elci, Orso | J95: Ambassador: Conte e Ambassadore | K95: Beaurocratic | O95: Non habbiamo risposto fin'hora alla prima lettera di VS de 29 7mbre (September), perche aspettiamo di Siena l'Informazione di quella supplica, ch'ella ci ha' inviata a' nome del s.r Cardinale Crescenzio, che non essendo ancora comparsa, ci e' parso di accusarlene senza piu' indugio la ricevuta, et quando havremo la d.a Informat.e, si cerchera' di servire il sud. s.r Cardinale di quel che si potra'; Ma' li due Bandi, che ha' il supplicanti, appariscono fin hora molto brutti., et Quanto alla 2.a [seconda?] lettera de' 30 del med[esim]o, Domani sara' qui il Cav.le Cioli, et sempre, che egli haura' da venire a' cotesta volta, segli daranno quegli ordini, et avvertimenti, che accenna VS pertrattare quel negotio con S. S.ta; et in proposito della Principessina sposa (is this Ferdinando's future bride Vittoria della Rovere?), che sara' qui domani, il tempo, et le occoninze ci governeranno per tenerla, o', ne nel Monast[e]rio della Crocetta appresso alla S.ra Principessa sua Madre (Claudia de' Medici, or someone else?), per li rispetti accennatici da VS, et faremo capitale del suo Consiglio, et ragioni scritte, et il s.re Iddio le conceda tutte le prosperita'; et rivedendosi ella col buon P're Dom. lo saluti da parte nra, et gli ricordi di nuovo il pregare per Noi. Di fiorenza 9 Ottobre 1623
A96: ID_00095 | B96: ASF, Acquisti e Doni, Fol 243, Ins 5. | C96: 53r | D96: 64 | E96: 1623/02/17 | F96: Firenze/Fiorenza | G96: von Habsburg, Maria Magdalena | H96: Ruler: Arciduchessa d'Austria e Gran Duchessa di Toscana | I96: d'Elci, Orso | J96: Ambassador: Conte e Ambassadore | K96: Beaurocratic | O96: Habbiamo resoluto Madama Ser.ma et Noi di continuare la solita limosina alli Deputati della Congregatione del B___ Ipolito ancora per sei mesi, accio possino tirare innanzi il Processo, che hanno fra' mano; et si come in cio' habbiamo seguitato il consiglio di VS, cosi le ne habbiamo voluto dare l'avviso, et si e' anche fatta sapere questa nra resoluzione alli med. Deputati; et ci pare anche dovere, che ella sappia, che Noi domattina, col favor di Dio, cene andiemo all'Ambrogiana, per fare il restante delle nostre Caccie, et per'arrivare poi a' Pisa gli ultimi giorni di Carnevale; et il Gran Duca, et Noi la salutiamo. Di fiorenza 7 febbraio 1623
A97: ID_00096 | B97: ASF, Acquisti e Doni, Fol 243, Ins 5. | C97: 55r | D97: 66 | E97: 1623/08/30 | F97: Firenze/Fiorenza | G97: von Habsburg, Maria Magdalena | H97: Ruler: Arciduchessa d'Austria e Gran Duchessa di Toscana | I97: d'Elci, Orso | J97: Ambassador: Conte e Ambassadore | K97: Beaurocratic | O97: VS. ci ringrazia con le opere, et Noi non ci stanchremo mai di riconscerle, cosi come le gradiamo. In tempo del suo destinato ritorno, speriamo di havere a essere in Siena, et si raginera' piu' volte della sua gita di Maremma, innanzi __ ella __ nadia, tengo in tanto VS salda questa mattina, che la vogliamo sana, come richide il nro bisogno. It el neg. del Conte Scipione (Borghese?) lasceremo dunque fare a s.r Cardinale pri_____ vede, che ne desidera ______, la febbe ritornata al Papa non ci lascia stare ___ta gelosia; et non cesseremo che aiutarlo con le orationi; et rimettendoci nel resto a q.le che le scrive Madama, la salutiamo; et Il __ Iddio la conservi, et contenti. De fiorenza 30 Ag. 1623
A98: ID_00097 | B98: ASF, Acquisti e Doni, Fol 243, Ins 5. | C98: 57r | D98: 68 | E98: 1623/01/25 | F98: Villa Poggio Imperiale | G98: von Habsburg, Maria Magdalena | H98: Ruler: Arciduchessa d'Austria e Gran Duchessa di Toscana | I98: d'Elci, Orso | J98: Ambassador: Conte e Ambassadore | K98: Beaurocratic
A99: ID_00098 | B99: ASF, Acquisti e Doni, Fol 243, Ins 5. | C99: 4r | D99: 7 | E99: 1623/00/19 | F99: Firenze/Fiorenza | G99: von Habsburg, Maria Magdalena | H99: Ruler: Arciduchessa d'Austria e Gran Duchessa di Toscana | I99: d'Elci, Orso | J99: Ambassador: Conte e Ambassadore | K99: Beaurocratic | O99: sig[nore] conto la sua lettera di x di questo mese mi fu reso in man__ propria del conte scipione suo figlio et me pare che V.S. faccia molto bene far venire scipione costi mentre sia anche lei perche la potra introdurre da se dove lei piacciara li mando anche con questa la lettera per il papa non so si sara a suo modo li me mando ad la lira aperta d__da la possa leggere et poi sigillare et havero caro che sia a suogusto et perche il lonte scipione medesimo sara ___ fatore di questa non voglio esser piu longa perche lui potera dare raguaglio a VS di ogni cosa come stiamo si non che speto _ con gran desiderio la sua tornata che spero habbia da esser presto perche non so si il pr[incipe?] Don lorenzo voglia piu andare _no come VS __ten___ di madama et Dio lo conservi di fiornza il di 19 di [looks like 9bre?] 1623
A100: ID_00099 | B100: ASF, Acquisti e Doni, Fol 243, Ins 5. | C100: 59r | D100: 70 | E100: 1623/02/07 | F100: Firenze/Fiorenza | G100: von Habsburg, Maria Magdalena | H100: Ruler: Arciduchessa d'Austria e Gran Duchessa di Toscana | I100: d'Elci, Orso | J100: Ambassador: Conte e Ambassadore | K100: Beaurocratic
...

Sheet Geographic Mapping
A1: {='Raw Data'!$A1:$A501} -> Unique ID | B1: {='Raw Data'!$E1:$E501} -> Date* | C1: {='Raw Data'!$F1:$F501} -> Source Location | D1: Source Latitude | E1: Source Longitude | F1: {='Raw Data'!$G1:$G501} -> Source | G1: {='Raw Data'!$I1:$I501} -> Target | H1: Target Location (Inferred) | I1: Target Latitude | J1: Target Longitude
A2: ID_00001 | B2: 1624/04/12 | C2: Pisa | D2: =_xlfn.XLOOKUP(C2,'Place Profiles'!A:A,'Place Profiles'!B:B,"0") -> 43.722514 | E2: =_xlfn.XLOOKUP(C2,'Place Profiles'!A:A,'Place Profiles'!C:C,"0") -> 10.396052 | F2: della Rena, Horatzio | G2: von Habsburg, Maria Magdalena | H2: {=_xlfn.LET( _xlpm.t,$G2, _xlpm.cands,_xlfn._xlws.FILTER('Place Profiles'!$G$2:$G$929,'Place Profiles'!$G$2:$G$929<>""), _xlpm.counts,COUNTIFS('Raw Data'!$G$2:$G$501,_xlpm.t,'Raw Data'!$F$2:$F$501,_xlpm.cands), _xlpm.mx,MAX(_xlpm.counts), IF(_xlpm.mx=0,0,_xlfn.TEXTJOIN(" / ",TRUE,_xlfn._xlws.FILTER(_xlpm.cands,_xlpm.counts=_xlpm.mx))) )} -> Firenze/Fiorenza | I2: =_xlfn.XLOOKUP(H2,'Place Profiles'!A:A,'Place Profiles'!B:B,"0") -> 43.773822 | J2: =_xlfn.XLOOKUP(H2,'Place Profiles'!A:A,'Place Profiles'!C:C,"0") -> 11.255536
A3: ID_00002 | B3: 1623/02/19 | C3: Pisa | D3: =_xlfn.XLOOKUP(C3,'Place Profiles'!A:A,'Place Profiles'!B:B,"0") -> 43.722514 | E3: =_xlfn.XLOOKUP(C3,'Place Profiles'!A:A,'Place Profiles'!C:C,"0") -> 10.396052 | F3: della Rena, Horatzio | G3: von Habsburg, Maria Magdalena | H3: {=_xlfn.LET( _xlpm.t,$G3, _xlpm.cands,_xlfn._xlws.FILTER('Place Profiles'!$G$2:$G$929,'Place Profiles'!$G$2:$G$929<>""), _xlpm.counts,COUNTIFS('Raw Data'!$G$2:$G$501,_xlpm.t,'Raw Data'!$F$2:$F$501,_xlpm.cands), _xlpm.mx,MAX(_xlpm.counts), IF(_xlpm.mx=0,0,_xlfn.TEXTJOIN(" / ",TRUE,_xlfn._xlws.FILTER(_xlpm.cands,_xlpm.counts=_xlpm.mx))) )} -> Firenze/Fiorenza | I3: =_xlfn.XLOOKUP(H3,'Place Profiles'!A:A,'Place Profiles'!B:B,"0") -> 43.773822 | J3: =_xlfn.XLOOKUP(H3,'Place Profiles'!A:A,'Place Profiles'!C:C,"0") -> 11.255536
A4: ID_00003 | B4: 1609/08/22 | C4: Firenze/Fiorenza | D4: =_xlfn.XLOOKUP(C4,'Place Profiles'!A:A,'Place Profiles'!B:B,"0") -> 43.773822 | E4: =_xlfn.XLOOKUP(C4,'Place Profiles'!A:A,'Place Profiles'!C:C,"0") -> 11.255536 | F4: von Habsburg, Maria Magdalena | G4: d'Elci, Orso | H4: {=_xlfn.LET( _xlpm.t,$G4, _xlpm.cands,_xlfn._xlws.FILTER('Place Profiles'!$G$2:$G$929,'Place Profiles'!$G$2:$G$929<>""), _xlpm.counts,COUNTIFS('Raw Data'!$G$2:$G$501,_xlpm.t,'Raw Data'!$F$2:$F$501,_xlpm.cands), _xlpm.mx,MAX(_xlpm.counts), IF(_xlpm.mx=0,0,_xlfn.TEXTJOIN(" / ",TRUE,_xlfn._xlws.FILTER(_xlpm.cands,_xlpm.counts=_xlpm.mx))) )} -> Siena | I4: =_xlfn.XLOOKUP(H4,'Place Profiles'!A:A,'Place Profiles'!B:B,"0") -> 43.318477 | J4: =_xlfn.XLOOKUP(H4,'Place Profiles'!A:A,'Place Profiles'!C:C,"0") -> 11.331079
A5: ID_00004 | B5: 1609/10/13 | C5: Firenze/Fiorenza | D5: =_xlfn.XLOOKUP(C5,'Place Profiles'!A:A,'Place Profiles'!B:B,"0") -> 43.773822 | E5: =_xlfn.XLOOKUP(C5,'Place Profiles'!A:A,'Place Profiles'!C:C,"0") -> 11.255536 | F5: von Habsburg, Maria Magdalena | G5: d'Elci, Orso | H5: {=_xlfn.LET( _xlpm.t,$G5, _xlpm.cands,_xlfn._xlws.FILTER('Place Profiles'!$G$2:$G$929,'Place Profiles'!$G$2:$G$929<>""), _xlpm.counts,COUNTIFS('Raw Data'!$G$2:$G$501,_xlpm.t,'Raw Data'!$F$2:$F$501,_xlpm.cands), _xlpm.mx,MAX(_xlpm.counts), IF(_xlpm.mx=0,0,_xlfn.TEXTJOIN(" / ",TRUE,_xlfn._xlws.FILTER(_xlpm.cands,_xlpm.counts=_xlpm.mx))) )} -> Siena | I5: =_xlfn.XLOOKUP(H5,'Place Profiles'!A:A,'Place Profiles'!B:B,"0") -> 43.318477 | J5: =_xlfn.XLOOKUP(H5,'Place Profiles'!A:A,'Place Profiles'!C:C,"0") -> 11.331079
A6: ID_00005 | B6: 1609/08/22 | C6: Firenze/Fiorenza | D6: =_xlfn.XLOOKUP(C6,'Place Profiles'!A:A,'Place Profiles'!B:B,"0") -> 43.773822 | E6: =_xlfn.XLOOKUP(C6,'Place Profiles'!A:A,'Place Profiles'!C:C,"0") -> 11.255536 | F6: von Habsburg, Maria Magdalena | G6: d'Elci, Orso | H6: {=_xlfn.LET( _xlpm.t,$G6, _xlpm.cands,_xlfn._xlws.FILTER('Place Profiles'!$G$2:$G$929,'Place Profiles'!$G$2:$G$929<>""), _xlpm.counts,COUNTIFS('Raw Data'!$G$2:$G$501,_xlpm.t,'Raw Data'!$F$2:$F$501,_xlpm.cands), _xlpm.mx,MAX(_xlpm.counts), IF(_xlpm.mx=0,0,_xlfn.TEXTJOIN(" / ",TRUE,_xlfn._xlws.FILTER(_xlpm.cands,_xlpm.counts=_xlpm.mx))) )} -> Siena | I6: =_xlfn.XLOOKUP(H6,'Place Profiles'!A:A,'Place Profiles'!B:B,"0") -> 43.318477 | J6: =_xlfn.XLOOKUP(H6,'Place Profiles'!A:A,'Place Profiles'!C:C,"0") -> 11.331079
A7: ID_00006 | B7: 1610/09/02 | C7: Firenze/Fiorenza | D7: =_xlfn.XLOOKUP(C7,'Place Profiles'!A:A,'Place Profiles'!B:B,"0") -> 43.773822 | E7: =_xlfn.XLOOKUP(C7,'Place Profiles'!A:A,'Place Profiles'!C:C,"0") -> 11.255536 | F7: von Habsburg, Maria Magdalena | G7: d'Elci, Orso | H7: {=_xlfn.LET( _xlpm.t,$G7, _xlpm.cands,_xlfn._xlws.FILTER('Place Profiles'!$G$2:$G$929,'Place Profiles'!$G$2:$G$929<>""), _xlpm.counts,COUNTIFS('Raw Data'!$G$2:$G$501,_xlpm.t,'Raw Data'!$F$2:$F$501,_xlpm.cands), _xlpm.mx,MAX(_xlpm.counts), IF(_xlpm.mx=0,0,_xlfn.TEXTJOIN(" / ",TRUE,_xlfn._xlws.FILTER(_xlpm.cands,_xlpm.counts=_xlpm.mx))) )} -> Siena | I7: =_xlfn.XLOOKUP(H7,'Place Profiles'!A:A,'Place Profiles'!B:B,"0") -> 43.318477 | J7: =_xlfn.XLOOKUP(H7,'Place Profiles'!A:A,'Place Profiles'!C:C,"0") -> 11.331079
A8: ID_00007 | B8: 1610/10/09 | C8: Firenze/Fiorenza | D8: =_xlfn.XLOOKUP(C8,'Place Profiles'!A:A,'Place Profiles'!B:B,"0") -> 43.773822 | E8: =_xlfn.XLOOKUP(C8,'Place Profiles'!A:A,'Place Profiles'!C:C,"0") -> 11.255536 | F8: von Habsburg, Maria Magdalena | G8: d'Elci, Orso | H8: {=_xlfn.LET( _xlpm.t,$G8, _xlpm.cands,_xlfn._xlws.FILTER('Place Profiles'!$G$2:$G$929,'Place Profiles'!$G$2:$G$929<>""), _xlpm.counts,COUNTIFS('Raw Data'!$G$2:$G$501,_xlpm.t,'Raw Data'!$F$2:$F$501,_xlpm.cands), _xlpm.mx,MAX(_xlpm.counts), IF(_xlpm.mx=0,0,_xlfn.TEXTJOIN(" / ",TRUE,_xlfn._xlws.FILTER(_xlpm.cands,_xlpm.counts=_xlpm.mx))) )} -> Siena | I8: =_xlfn.XLOOKUP(H8,'Place Profiles'!A:A,'Place Profiles'!B:B,"0") -> 43.318477 | J8: =_xlfn.XLOOKUP(H8,'Place Profiles'!A:A,'Place Profiles'!C:C,"0") -> 11.331079
A9: ID_00008 | B9: 1610/12/01 | C9: Firenze/Fiorenza | D9: =_xlfn.XLOOKUP(C9,'Place Profiles'!A:A,'Place Profiles'!B:B,"0") -> 43.773822 | E9: =_xlfn.XLOOKUP(C9,'Place Profiles'!A:A,'Place Profiles'!C:C,"0") -> 11.255536 | F9: von Habsburg, Maria Magdalena | G9: d'Elci, Orso | H9: {=_xlfn.LET( _xlpm.t,$G9, _xlpm.cands,_xlfn._xlws.FILTER('Place Profiles'!$G$2:$G$929,'Place Profiles'!$G$2:$G$929<>""), _xlpm.counts,COUNTIFS('Raw Data'!$G$2:$G$501,_xlpm.t,'Raw Data'!$F$2:$F$501,_xlpm.cands), _xlpm.mx,MAX(_xlpm.counts), IF(_xlpm.mx=0,0,_xlfn.TEXTJOIN(" / ",TRUE,_xlfn._xlws.FILTER(_xlpm.cands,_xlpm.counts=_xlpm.mx))) )} -> Siena | I9: =_xlfn.XLOOKUP(H9,'Place Profiles'!A:A,'Place Profiles'!B:B,"0") -> 43.318477 | J9: =_xlfn.XLOOKUP(H9,'Place Profiles'!A:A,'Place Profiles'!C:C,"0") -> 11.331079
A10: ID_00009 | B10: 1610/02/10 | C10: Firenze/Fiorenza | D10: =_xlfn.XLOOKUP(C10,'Place Profiles'!A:A,'Place Profiles'!B:B,"0") -> 43.773822 | E10: =_xlfn.XLOOKUP(C10,'Place Profiles'!A:A,'Place Profiles'!C:C,"0") -> 11.255536 | F10: von Habsburg, Maria Magdalena | G10: d'Elci, Orso | H10: {=_xlfn.LET( _xlpm.t,$G10, _xlpm.cands,_xlfn._xlws.FILTER('Place Profiles'!$G$2:$G$929,'Place Profiles'!$G$2:$G$929<>""), _xlpm.counts,COUNTIFS('Raw Data'!$G$2:$G$501,_xlpm.t,'Raw Data'!$F$2:$F$501,_xlpm.cands), _xlpm.mx,MAX(_xlpm.counts), IF(_xlpm.mx=0,0,_xlfn.TEXTJOIN(" / ",TRUE,_xlfn._xlws.FILTER(_xlpm.cands,_xlpm.counts=_xlpm.mx))) )} -> Siena | I10: =_xlfn.XLOOKUP(H10,'Place Profiles'!A:A,'Place Profiles'!B:B,"0") -> 43.318477 | J10: =_xlfn.XLOOKUP(H10,'Place Profiles'!A:A,'Place Profiles'!C:C,"0") -> 11.331079
A11: ID_00010 | B11: 1611/06/08 | C11: Firenze/Fiorenza | D11: =_xlfn.XLOOKUP(C11,'Place Profiles'!A:A,'Place Profiles'!B:B,"0") -> 43.773822 | E11: =_xlfn.XLOOKUP(C11,'Place Profiles'!A:A,'Place Profiles'!C:C,"0") -> 11.255536 | F11: von Habsburg, Maria Magdalena | G11: d'Elci, Orso | H11: {=_xlfn.LET( _xlpm.t,$G11, _xlpm.cands,_xlfn._xlws.FILTER('Place Profiles'!$G$2:$G$929,'Place Profiles'!$G$2:$G$929<>""), _xlpm.counts,COUNTIFS('Raw Data'!$G$2:$G$501,_xlpm.t,'Raw Data'!$F$2:$F$501,_xlpm.cands), _xlpm.mx,MAX(_xlpm.counts), IF(_xlpm.mx=0,0,_xlfn.TEXTJOIN(" / ",TRUE,_xlfn._xlws.FILTER(_xlpm.cands,_xlpm.counts=_xlpm.mx))) )} -> Siena | I11: =_xlfn.XLOOKUP(H11,'Place Profiles'!A:A,'Place Profiles'!B:B,"0") -> 43.318477 | J11: =_xlfn.XLOOKUP(H11,'Place Profiles'!A:A,'Place Profiles'!C:C,"0") -> 11.331079
A12: ID_00011 | B12: 1611/07/22 | C12: Firenze/Fiorenza | D12: =_xlfn.XLOOKUP(C12,'Place Profiles'!A:A,'Place Profiles'!B:B,"0") -> 43.773822 | E12: =_xlfn.XLOOKUP(C12,'Place Profiles'!A:A,'Place Profiles'!C:C,"0") -> 11.255536 | F12: von Habsburg, Maria Magdalena | G12: d'Elci, Orso | H12: {=_xlfn.LET( _xlpm.t,$G12, _xlpm.cands,_xlfn._xlws.FILTER('Place Profiles'!$G$2:$G$929,'Place Profiles'!$G$2:$G$929<>""), _xlpm.counts,COUNTIFS('Raw Data'!$G$2:$G$501,_xlpm.t,'Raw Data'!$F$2:$F$501,_xlpm.cands), _xlpm.mx,MAX(_xlpm.counts), IF(_xlpm.mx=0,0,_xlfn.TEXTJOIN(" / ",TRUE,_xlfn._xlws.FILTER(_xlpm.cands,_xlpm.counts=_xlpm.mx))) )} -> Siena | I12: =_xlfn.XLOOKUP(H12,'Place Profiles'!A:A,'Place Profiles'!B:B,"0") -> 43.318477 | J12: =_xlfn.XLOOKUP(H12,'Place Profiles'!A:A,'Place Profiles'!C:C,"0") -> 11.331079
A13: ID_00012 | B13: 1611/09/12 | C13: Firenze/Fiorenza | D13: =_xlfn.XLOOKUP(C13,'Place Profiles'!A:A,'Place Profiles'!B:B,"0") -> 43.773822 | E13: =_xlfn.XLOOKUP(C13,'Place Profiles'!A:A,'Place Profiles'!C:C,"0") -> 11.255536 | F13: von Habsburg, Maria Magdalena | G13: d'Elci, Orso | H13: {=_xlfn.LET( _xlpm.t,$G13, _xlpm.cands,_xlfn._xlws.FILTER('Place Profiles'!$G$2:$G$929,'Place Profiles'!$G$2:$G$929<>""), _xlpm.counts,COUNTIFS('Raw Data'!$G$2:$G$501,_xlpm.t,'Raw Data'!$F$2:$F$501,_xlpm.cands), _xlpm.mx,MAX(_xlpm.counts), IF(_xlpm.mx=0,0,_xlfn.TEXTJOIN(" / ",TRUE,_xlfn._xlws.FILTER(_xlpm.cands,_xlpm.counts=_xlpm.mx))) )} -> Siena | I13: =_xlfn.XLOOKUP(H13,'Place Profiles'!A:A,'Place Profiles'!B:B,"0") -> 43.318477 | J13: =_xlfn.XLOOKUP(H13,'Place Profiles'!A:A,'Place Profiles'!C:C,"0") -> 11.331079
... A501: ID_00500 | B501: 1620/11/02 | C501: Siena | D501: =_xlfn.XLOOKUP(C501,'Place Profiles'!A:A,'Place Profiles'!B:B,"0") -> 43.318477 | E501: =_xlfn.XLOOKUP(C501,'Place Profiles'!A:A,'Place Profiles'!C:C,"0") -> 11.331079 | F501: Colomba | G501: von Habsburg, Maria Magdalena | H501: {=_xlfn.LET( _xlpm.t,$G501, _xlpm.cands,_xlfn._xlws.FILTER('Place Profiles'!$G$2:$G$929,'Place Profiles'!$G$2:$G$929<>""), _xlpm.counts,COUNTIFS('Raw Data'!$G$2:$G$501,_xlpm.t,'Raw Data'!$F$2:$F$501,_xlpm.cands), _xlpm.mx,MAX(_xlpm.counts), IF(_xlpm.mx=0,0,_xlfn.TEXTJOIN(" / ",TRUE,_xlfn._xlws.FILTER(_xlpm.cands,_xlpm.counts=_xlpm.mx))) )} -> Firenze/Fiorenza | I501: =_xlfn.XLOOKUP(H501,'Place Profiles'!A:A,'Place Profiles'!B:B,"0") -> 43.773822 | J501: =_xlfn.XLOOKUP(H501,'Place Profiles'!A:A,'Place Profiles'!C:C,"0") -> 11.255536

Sheet Place Profiles
A1: Source Location | B1: Latitude | C1: Longitude | G1: All Locations (Updating) | H1: In A or not?
A2: __erero | B2: 0 | C2: 0 | E2: <-- Static list of locations and coordinates | G2: {=_xlfn._xlws.SORT(_xlfn.UNIQUE(_xlfn._xlws.FILTER('Raw Data'!F2:F501,'Raw Data'!F2:F501<>"")))} -> Acquapend.te | H2: =IF(COUNTIF($A:$A,G2)=0,"NEW","") | J2: <-- Updating list of all mentioned locations
A3: __mercato | B3: 0 | C3: 0 | G3: Ambrogiana | H3: =IF(COUNTIF($A:$A,G3)=0,"NEW","")
A4: A___ | B4: 0 | C4: 0 | G4: Cafaggiuolo | H4: =IF(COUNTIF($A:$A,G4)=0,"NEW","")
A5: Acquapend.te | B5: 42.745151 | C5: 11.863983 | G5: Camerino | H5: =IF(COUNTIF($A:$A,G5)=0,"NEW","")
A6: Alexandria | B6: 0 | C6: 0 | G6: Case Nuove | H6: =IF(COUNTIF($A:$A,G6)=0,"NEW","")
A7: Ambrogiana | B7: 43.731062 | C7: 11.014485 | G7: Cortona | H7: =IF(COUNTIF($A:$A,G7)=0,"NEW","")
A8: Arrezo | B8: 43.463115 | C8: 11.878862 | G8: Firenze nel Monasterio della Santissima Concezzione | H8: =IF(COUNTIF($A:$A,G8)=0,"NEW","")
A9: Barone | B9: 0 | C9: 0 | G9: Firenze/Fiorenza | H9: =IF(COUNTIF($A:$A,G9)=0,"NEW","")
A10: Barracelli | B10: 43.750267 | C10: 11.247396 | G10: Fuligno | H10: =IF(COUNTIF($A:$A,G10)=0,"NEW","")
A11: Bergamo | B11: 45.694352 | C11: 9.6698331 | G11: Giglio | H11: =IF(COUNTIF($A:$A,G11)=0,"NEW","")
A12: Bologna | B12: 44.493631 | C12: 11.33854 | G12: Gross[ett]o | H12: =IF(COUNTIF($A:$A,G12)=0,"NEW","")
A13: Borgo | B13: 0 | C13: 0 | G13: Grosseto | H13: =IF(COUNTIF($A:$A,G13)=0,"NEW","")
A14: Borgo val di Taro | B14: 44.487731 | C14: 9.7675634 | G14: Guglio | H14: =IF(COUNTIF($A:$A,G14)=0,"NEW","")
... A38: Genova | B38: 44.409885 | C38: 8.9364926 | G38: Villa Poggio Imperiale | H38: =IF(COUNTIF($A:$A,G38)=0,"NEW","")
A39: Giglio | B39: 42.360515 | C39: 10.901171 | H39: =IF(COUNTIF($A:$A,G39)=0,"NEW","") -> NEW
A40: Gradisca | B40: 45.8913 | C40: 13.494655 | H40: =IF(COUNTIF($A:$A,G40)=0,"NEW","") -> NEW
A41: Gross[ett]o | B41: 42.763567 | C41: 11.110316 | H41: =IF(COUNTIF($A:$A,G41)=0,"NEW","") -> NEW
A42: Grosseto | B42: 42.763567 | C42: 11.110316 | H42: =IF(COUNTIF($A:$A,G42)=0,"NEW","") -> NEW
A43: Guglio | B43: 42.360515 | C43: 10.901171 | H43: =IF(COUNTIF($A:$A,G43)=0,"NEW","") -> NEW
A44: Illegible | B44: 0 | C44: 0 | H44: =IF(COUNTIF($A:$A,G44)=0,"NEW","") -> NEW
A45: Imperiale | B45: 43.750267 | C45: 11.247396 | H45: =IF(COUNTIF($A:$A,G45)=0,"NEW","") -> NEW
A46: Imprudenta | B46: 43.68583 | C46: 11.254096 | H46: =IF(COUNTIF($A:$A,G46)=0,"NEW","") -> NEW
A47: Impruneta | B47: 43.68583 | C47: 11.254096 | H47: =IF(COUNTIF($A:$A,G47)=0,"NEW","") -> NEW
A48: Inspruch | B48: 47.266114 | C48: 11.392466 | H48: =IF(COUNTIF($A:$A,G48)=0,"NEW","") -> NEW
A49: La Riva | B49: 44.801472 | C49: 10.328 | H49: =IF(COUNTIF($A:$A,G49)=0,"NEW","") -> NEW
A50: Livorno | B50: 43.551047 | C50: 10.306736 | H50: =IF(COUNTIF($A:$A,G50)=0,"NEW","") -> NEW
... A111: Villa Poggio Imperiale | B111: 43.750267 | C111: 11.247396 | H111: =IF(COUNTIF($A:$A,G111)=0,"NEW","") -> NEW

Sheet Drop Down Lists
B1: Relationships | D1: Cipher | F1: Topics | H1: Language | J1: Occupation
B2: Beaurocratic | D2: Most-All | F2: Austria | H2: French | J2: Beaurocrat
B3: Clerical | D3: None | F3: Avvisi | H3: German | J3: Clergy
B4: Close Blood Family | D4: Some | F4: Childbirth | H4: Italian | J4: Diplomat
B5: Close Marital Family | F5: Conclave | H5: Latin | J5: Merchant
B6: Diplomatic | F6: Condolences | H6: Spanish | J6: Nobility
B7: Extended Family | F7: Congratulations | J7: Ruler
B8: Nobles | F8: Death | J8: Scholar
B9: Subjects | F9: Death of Cosimo II
B10: Unknown | F10: Death of Maria Maddalena
F11: Holiday
F12: Illness
F13: Intelligence
F14: Inventory
F15: La Crocetta
F16: Loreto
F17: Marriage Negotiation
F18: Medical
F19: Military
F20: Officiali di Balia di Siena
F21: Papal Brevi
F22: Politics
... F30: War
